Workbook

Sheet projetos
A1: id | B1: nome | C1: squad | D1: status | E1: ordem_status | F1: etapa_cronograma | G1: is_backoffice | H1: bp | I1: desenvolvedor | J1: facilitador | K1: sponsor | L1: setor | M1: prioridade | N1: data_inicio | O1: data_fim | P1: duração_prev_dias | Q1: data_inicio_real | R1: data_fim_real | S1: duração_real_dias | T1: progresso_pct | U1: observação | V1: Horas economizadas anuais | W1: Horas economizadas semana | X1: Retorno Previsto $ | Y1: Retorno Gerado $ | Z1: capex | AA1: opex | AB1: spent_capex | AC1: spent_opex | AD1: expected_roi | AE1: payback_months | AF1: Nota Impacto | AG1: Nota Complexidade | AH1: Nota Valor | AI1: descricao | AJ1: nid_recommendation | AK1: Data Pedido PMO | AL1: Data Fim PMO | AM1: SLA Backlog | AN1: Data Inicio Prototipagem | AO1: Data Fim Prototipagem2 | AP1: SLA Prototipagem | AQ1: Capex IN | AR1: Capex OUT
A2: PRJ-025 | B2: Automação - R.A em avanço | C2: Automações RPA | D2: Encerrado | E2: =_xlfn.XLOOKUP(D2,validacao_lista!D:D,validacao_lista!E:E) -> 8 | F2: Implantação e Monitoramento | G2: =IFERROR(_xlfn.XLOOKUP(Tabela2[[#This Row],[setor]],dim_custo_setor_horas!A:A,dim_custo_setor_horas!C:C)," ") -> 0 | H2: Henrique Emiliano | I2: Henrique Emiliano | J2: Carlos Meinberg | K2: Claudio M | L2: Planejamento PCP - Filial | M2: 3 | N2: 45992 | O2: 46011 | P2: =Tabela2[[#This Row],[data_fim]]-Tabela2[[#This Row],[data_inicio]] -> 19 | Q2: 45992 | R2: 46011 | T2: 100 | V2: 540 | W2: =((Tabela2[[#This Row],[Horas economizadas anuais]] / 12) / 4) -> 11.25 | X2: =(_xlfn.XLOOKUP(Tabela2[[#This Row],[setor]],dim_custo_setor_horas!A:A,dim_custo_setor_horas!B:B))*Tabela2[[#This Row],[Horas economizadas anuais]] -> 35299.8 | Y2: =IF(Tabela2[[#This Row],[progresso_pct]]=100,Tabela2[[#This Row],[Retorno Previsto $]],0) -> 35299.8 | Z2: =Tabela2[[#This Row],[duração_prev_dias]]*100 -> 1900 | AB2: 1900 | AC2: 420 | AD2: =IF(Tabela2[[#This Row],[progresso_pct]] = 100,IFERROR((Tabela2[[#This Row],[Retorno Previsto $]]-Tabela2[[#This Row],[spent_capex]])/Tabela2[[#This Row],[spent_capex]]," ")," ") -> 17.578842 | AE2: 16 | AF2: 3 | AG2: 3 | AH2: 3 | AI2: Automação de um flluxo completo de solicitação de R.A | AK2: - | AL2: - | AM2: =IFERROR(Tabela2[[#This Row],[Data Fim PMO]]-Tabela2[[#This Row],[Data Pedido PMO]],"") | AN2: 45992 | AO2: 46011 | AP2: =IF(Tabela2[[#This Row],[Data Fim Prototipagem2]]=0," ",IFERROR(Tabela2[[#This Row],[Data Fim Prototipagem2]]-Tabela2[[#This Row],[Data Inicio Prototipagem]],"")) -> 19 | AQ2: =Tabela2[[#This Row],[capex]] -> 1900 | AR2: =Tabela2[[#This Row],[Capex IN]]-Tabela2[[#This Row],[capex]] -> 0
A3: PRJ-026 | B3: Automação - Visão da rotina | C3: Automações RPA | D3: Encerrado | E3: =_xlfn.XLOOKUP(D3,validacao_lista!D:D,validacao_lista!E:E) -> 8 | F3: Implantação e Monitoramento | G3: =IFERROR(_xlfn.XLOOKUP(Tabela2[[#This Row],[setor]],dim_custo_setor_horas!A:A,dim_custo_setor_horas!C:C)," ") -> 0 | H3: Luiz Castro | I3: Luiz Castro | J3: Carlos Meinberg | K3: Claudio M | L3: Planejamento PCP - Filial | M3: 3 | N3: 46063 | O3: 46068 | P3: =Tabela2[[#This Row],[data_fim]]-Tabela2[[#This Row],[data_inicio]] -> 5 | Q3: 45992 | R3: 46068 | T3: 100 | V3: 589 | W3: =((Tabela2[[#This Row],[Horas economizadas anuais]] / 12) / 4) -> 12.270833 | X3: =(_xlfn.XLOOKUP(Tabela2[[#This Row],[setor]],dim_custo_setor_horas!A:A,dim_custo_setor_horas!B:B))*Tabela2[[#This Row],[Horas economizadas anuais]] -> 38502.93 | Y3: =IF(Tabela2[[#This Row],[progresso_pct]]=100,Tabela2[[#This Row],[Retorno Previsto $]],0) -> 38502.93 | Z3: =Tabela2[[#This Row],[duração_prev_dias]]*100 -> 500 | AB3: 500 | AC3: 420 | AD3: =IF(Tabela2[[#This Row],[progresso_pct]] = 100,IFERROR((Tabela2[[#This Row],[Retorno Previsto $]]-Tabela2[[#This Row],[spent_capex]])/Tabela2[[#This Row],[spent_capex]]," ")," ") -> 76.00586 | AE3: 16 | AF3: 3 | AG3: 3 | AH3: 3 | AI3: Automação de preenchimento e envio de informações semanais | AK3: - | AL3: - | AM3: =IFERROR(Tabela2[[#This Row],[Data Fim PMO]]-Tabela2[[#This Row],[Data Pedido PMO]],"") | AN3: 45992 | AO3: 46068 | AP3: =IF(Tabela2[[#This Row],[Data Fim Prototipagem2]]=0," ",IFERROR(Tabela2[[#This Row],[Data Fim Prototipagem2]]-Tabela2[[#This Row],[Data Inicio Prototipagem]],"")) -> 76 | AQ3: =Tabela2[[#This Row],[capex]] -> 500
A4: PRJ-012 | B4: BI Controle Projetos - Fase - Sala verde | C4: BI & Eng. Dados | D4: Encerrado | E4: =_xlfn.XLOOKUP(D4,validacao_lista!D:D,validacao_lista!E:E) -> 8 | F4: Implantação e Monitoramento | G4: =IFERROR(_xlfn.XLOOKUP(Tabela2[[#This Row],[setor]],dim_custo_setor_horas!A:A,dim_custo_setor_horas!C:C)," ") -> 0 | H4: Henrique Emiliano | I4: Henrique Emiliano | J4: Carlos Meinberg | K4: Claudio M | L4: Planejamento PCP - Filial | M4: 3 | N4: 45931 | O4: 46023 | P4: =Tabela2[[#This Row],[data_fim]]-Tabela2[[#This Row],[data_inicio]] -> 92 | Q4: 45931 | R4: 46023 | T4: 100 | V4: 768 | W4: =((Tabela2[[#This Row],[Horas economizadas anuais]] / 12) / 4) -> 16 | X4: =(_xlfn.XLOOKUP(Tabela2[[#This Row],[setor]],dim_custo_setor_horas!A:A,dim_custo_setor_horas!B:B))*Tabela2[[#This Row],[Horas economizadas anuais]] -> 50204.16 | Y4: =IF(Tabela2[[#This Row],[progresso_pct]]=100,Tabela2[[#This Row],[Retorno Previsto $]],0) -> 50204.16 | Z4: =Tabela2[[#This Row],[duração_prev_dias]]*100 -> 9200 | AB4: 9200 | AC4: 420 | AD4: =IF(Tabela2[[#This Row],[progresso_pct]] = 100,IFERROR((Tabela2[[#This Row],[Retorno Previsto $]]-Tabela2[[#This Row],[spent_capex]])/Tabela2[[#This Row],[spent_capex]]," ")," ") -> 4.4569739 | AE4: 16 | AF4: 3 | AG4: 5 | AH4: 3 | AI4: BI controle interno de projetos - Pasta 36 | AJ4: revisar | AK4: - | AL4: - | AM4: =IFERROR(Tabela2[[#This Row],[Data Fim PMO]]-Tabela2[[#This Row],[Data Pedido PMO]],"") | AN4: 45931 | AO4: 46023 | AP4: =IF(Tabela2[[#This Row],[Data Fim Prototipagem2]]=0," ",IFERROR(Tabela2[[#This Row],[Data Fim Prototipagem2]]-Tabela2[[#This Row],[Data Inicio Prototipagem]],"")) -> 92 | AQ4: =Tabela2[[#This Row],[capex]] -> 9200
A5: PRJ-024 | B5: Automação - Eficiência por célula | C5: Automações RPA | D5: Encerrado | E5: =_xlfn.XLOOKUP(D5,validacao_lista!D:D,validacao_lista!E:E) -> 8 | F5: Implantação e Monitoramento | G5: =IFERROR(_xlfn.XLOOKUP(Tabela2[[#This Row],[setor]],dim_custo_setor_horas!A:A,dim_custo_setor_horas!C:C)," ") -> 0 | H5: Luiz Castro | I5: Luiz Castro | J5: Chistiane | K5: Claudio M | L5: Planejamento PCP - Filial | M5: 3 | N5: 46063 | O5: 46068 | P5: =Tabela2[[#This Row],[data_fim]]-Tabela2[[#This Row],[data_inicio]] -> 5 | Q5: 46064 | T5: 100 | V5: =288 -> 288 | W5: =((Tabela2[[#This Row],[Horas economizadas anuais]] / 12) / 4) -> 6 | X5: =(_xlfn.XLOOKUP(Tabela2[[#This Row],[setor]],dim_custo_setor_horas!A:A,dim_custo_setor_horas!B:B))*Tabela2[[#This Row],[Horas economizadas anuais]] -> 18826.56 | Y5: =IF(Tabela2[[#This Row],[progresso_pct]]=100,Tabela2[[#This Row],[Retorno Previsto $]],0) -> 18826.56 | Z5: =Tabela2[[#This Row],[duração_prev_dias]]*100 -> 500 | AB5: =Tabela2[[#This Row],[capex]] -> 500 | AC5: 420 | AD5: =IFERROR((Tabela2[[#This Row],[Retorno Previsto $]]-Tabela2[[#This Row],[spent_capex]])/Tabela2[[#This Row],[spent_capex]]," ") -> 36.65312 | AE5: 16 | AF5: 3 | AG5: 5 | AH5: 3 | AI5: Automação de preenchimento e envio de informações semanais | AK5: - | AL5: - | AM5: =IFERROR(Tabela2[[#This Row],[Data Fim PMO]]-Tabela2[[#This Row],[Data Pedido PMO]],"") | AN5: 46063 | AP5: =IF(Tabela2[[#This Row],[Data Fim Prototipagem2]]=0," ",IFERROR(Tabela2[[#This Row],[Data Fim Prototipagem2]]-Tabela2[[#This Row],[Data Inicio Prototipagem]],"")) | AQ5: =Tabela2[[#This Row],[capex]] -> 500
A6: PRJ-029 | B6: Melhorias Core (BI - Registro da Qualidade) | C6: BI & Eng. Dados | D6: Encerrado | E6: =_xlfn.XLOOKUP(D6,validacao_lista!D:D,validacao_lista!E:E) -> 8 | F6: Implantação e Monitoramento | G6: =IFERROR(_xlfn.XLOOKUP(Tabela2[[#This Row],[setor]],dim_custo_setor_horas!A:A,dim_custo_setor_horas!C:C)," ") -> 0 | H6: Lucas Franca | I6: Lucas Franca | J6: Ana C. Viana | K6: Paulo Henrique | L6: Controle de Qualidade - Filial | M6: 1 | N6: 46076 | O6: 46087 | P6: =Tabela2[[#This Row],[data_fim]]-Tabela2[[#This Row],[data_inicio]] -> 11 | Q6: 46076 | R6: 46087 | T6: 100 | V6: 600 | W6: =((Tabela2[[#This Row],[Horas economizadas anuais]] / 12) / 4) -> 12.5 | X6: =(_xlfn.XLOOKUP(Tabela2[[#This Row],[setor]],dim_custo_setor_horas!A:A,dim_custo_setor_horas!B:B))*Tabela2[[#This Row],[Horas economizadas anuais]] -> 44766 | Y6: =IF(Tabela2[[#This Row],[progresso_pct]]=100,Tabela2[[#This Row],[Retorno Previsto $]],0) -> 44766 | Z6: 1600 | AB6: 1600 | AD6: =IF(Tabela2[[#This Row],[progresso_pct]] = 100,IFERROR((Tabela2[[#This Row],[Retorno Previsto $]]-Tabela2[[#This Row],[spent_capex]])/Tabela2[[#This Row],[spent_capex]]," ")," ") -> 26.97875 | AI6: BI - Registro da Qualidade | AJ6: aprovado | AM6: =IFERROR(Tabela2[[#This Row],[Data Fim PMO]]-Tabela2[[#This Row],[Data Pedido PMO]],"") -> 0 | AP6: =IF(Tabela2[[#This Row],[Data Fim Prototipagem2]]=0," ",IFERROR(Tabela2[[#This Row],[Data Fim Prototipagem2]]-Tabela2[[#This Row],[Data Inicio Prototipagem]],"")) | AQ6: 1600
A7: PRJ-035 | B7: Automação - Float | C7: Automações RPA | D7: Encerrado | E7: =_xlfn.XLOOKUP(D7,validacao_lista!D:D,validacao_lista!E:E) -> 8 | F7: Implantação e Monitoramento | G7: =IFERROR(_xlfn.XLOOKUP(Tabela2[[#This Row],[setor]],dim_custo_setor_horas!A:A,dim_custo_setor_horas!C:C)," ") -> 0 | H7: Luiz Castro | I7: Luiz Castro | J7: Carlos Meinberg | K7: Claudio M | L7: Planejamento PCP - Filial | M7: 3 | N7: 46090 | O7: 46090 | P7: =Tabela2[[#This Row],[data_fim]]-Tabela2[[#This Row],[data_inicio]] -> 0 | T7: 0 | V7: 240 | W7: =((Tabela2[[#This Row],[Horas economizadas anuais]] / 12) / 4) -> 5 | X7: =(_xlfn.XLOOKUP(Tabela2[[#This Row],[setor]],dim_custo_setor_horas!A:A,dim_custo_setor_horas!B:B))*Tabela2[[#This Row],[Horas economizadas anuais]] -> 15688.8 | Y7: =IF(Tabela2[[#This Row],[progresso_pct]]=100,Tabela2[[#This Row],[Retorno Previsto $]],0) -> 0 | Z7: 800 | AD7: =IF(Tabela2[[#This Row],[progresso_pct]] = 100,IFERROR((Tabela2[[#This Row],[Retorno Previsto $]]-Tabela2[[#This Row],[spent_capex]])/Tabela2[[#This Row],[spent_capex]]," ")," ") | AF7: 3 | AG7: 3 | AH7: 3 | AI7: Controle contratos manufatura no Fluig/RM | AJ7: revisar | AK7: - | AL7: - | AM7: =IFERROR(Tabela2[[#This Row],[Data Fim PMO]]-Tabela2[[#This Row],[Data Pedido PMO]],"") | AP7: =IF(Tabela2[[#This Row],[Data Fim Prototipagem2]]=0," ",IFERROR(Tabela2[[#This Row],[Data Fim Prototipagem2]]-Tabela2[[#This Row],[Data Inicio Prototipagem]],"")) | AQ7: 500
A8: PRJ-001 | B8: BI People Analytics RH | C8: BI & Eng. Dados | D8: Estabilização | E8: =_xlfn.XLOOKUP(D8,validacao_lista!D:D,validacao_lista!E:E) -> 7 | F8: Implantação e Monitoramento | G8: =IFERROR(_xlfn.XLOOKUP(Tabela2[[#This Row],[setor]],dim_custo_setor_horas!A:A,dim_custo_setor_horas!C:C)," ") -> 1 | H8: Rafael Souza | I8: Henrique Emiliano | J8: Gleizieny | K8: Edilaine | L8: Gente e Gestão | M8: 1 | N8: 45992 | O8: 46112 | P8: =Tabela2[[#This Row],[data_fim]]-Tabela2[[#This Row],[data_inicio]] -> 120 | Q8: 45992 | T8: 99 | V8: 600 | W8: =((Tabela2[[#This Row],[Horas economizadas anuais]] / 12) / 4) -> 12.5 | X8: =(_xlfn.XLOOKUP(Tabela2[[#This Row],[setor]],dim_custo_setor_horas!A:A,dim_custo_setor_horas!B:B))*Tabela2[[#This Row],[Horas economizadas anuais]] -> 60516 | Y8: =IF(Tabela2[[#This Row],[progresso_pct]]=100,Tabela2[[#This Row],[Retorno Previsto $]],0) -> 0 | Z8: =Tabela2[[#This Row],[duração_prev_dias]]*100 -> 12000 | AB8: =Tabela2[[#This Row],[capex]] -> 12000 | AC8: 800 | AD8: =IF(Tabela2[[#This Row],[progresso_pct]] = 100,IFERROR((Tabela2[[#This Row],[Retorno Previsto $]]-Tabela2[[#This Row],[spent_capex]])/Tabela2[[#This Row],[spent_capex]]," ")," ") | AE8: 10 | AF8: 3 | AG8: 3 | AH8: 3 | AI8: Dashboard People Analytics para RH | AJ8: aprovar | AK8: 46029 | AL8: 46029 | AM8: =IFERROR(Tabela2[[#This Row],[Data Fim PMO]]-Tabela2[[#This Row],[Data Pedido PMO]],"") -> 0 | AN8: 46030 | AO8: 46031 | AP8: =IF(Tabela2[[#This Row],[Data Fim Prototipagem2]]=0," ",IFERROR(Tabela2[[#This Row],[Data Fim Prototipagem2]]-Tabela2[[#This Row],[Data Inicio Prototipagem]],"")) -> 1 | AQ8: =Tabela2[[#This Row],[capex]] -> 12000
A9: PRJ-002 | B9: BI SGQ | C9: BI & Eng. Dados | D9: Go Live | E9: =_xlfn.XLOOKUP(D9,validacao_lista!D:D,validacao_lista!E:E) -> 6 | F9: Implantação e Monitoramento | G9: =IFERROR(_xlfn.XLOOKUP(Tabela2[[#This Row],[setor]],dim_custo_setor_horas!A:A,dim_custo_setor_horas!C:C)," ") -> 1 | H9: Rafael Souza | I9: Henrique Emiliano | J9: Keila | K9: Luiz Henrique | L9: SGQ - Filial | M9: 1 | N9: 46054 | O9: 46112 | P9: =Tabela2[[#This Row],[data_fim]]-Tabela2[[#This Row],[data_inicio]] -> 58 | Q9: 46054 | T9: 90 | V9: 420 | W9: =((Tabela2[[#This Row],[Horas economizadas anuais]] / 12) / 4) -> 8.75 | X9: =(_xlfn.XLOOKUP(Tabela2[[#This Row],[setor]],dim_custo_setor_horas!A:A,dim_custo_setor_horas!B:B))*Tabela2[[#This Row],[Horas economizadas anuais]] -> 31336.2 | Y9: =IF(Tabela2[[#This Row],[progresso_pct]]=100,Tabela2[[#This Row],[Retorno Previsto $]],0) -> 0 | Z9: =Tabela2[[#This Row],[duração_prev_dias]]*100 -> 5800 | AB9: =Tabela2[[#This Row],[capex]] -> 5800 | AC9: 600 | AD9: =IF(Tabela2[[#This Row],[progresso_pct]] = 100,IFERROR((Tabela2[[#This Row],[Retorno Previsto $]]-Tabela2[[#This Row],[spent_capex]])/Tabela2[[#This Row],[spent_capex]]," ")," ") | AE9: 11 | AF9: 3 | AG9: 3 | AH9: 3 | AI9: BI para Sistema de Gestão da Qualidade | AJ9: aprovar | AK9: 46029 | AL9: 46029 | AM9: =IFERROR(Tabela2[[#This Row],[Data Fim PMO]]-Tabela2[[#This Row],[Data Pedido PMO]],"") -> 0 | AN9: 46029 | AO9: 46030 | AP9: =IF(Tabela2[[#This Row],[Data Fim Prototipagem2]]=0," ",IFERROR(Tabela2[[#This Row],[Data Fim Prototipagem2]]-Tabela2[[#This Row],[Data Inicio Prototipagem]],"")) -> 1 | AQ9: =Tabela2[[#This Row],[capex]] -> 5800
A10: PRJ-031 | B10: Central de Indicadores Delp | C10: BI & Eng. Dados | D10: Go Live | E10: =_xlfn.XLOOKUP(D10,validacao_lista!D:D,validacao_lista!E:E) -> 6 | F10: Implantação e Monitoramento | G10: =IFERROR(_xlfn.XLOOKUP(Tabela2[[#This Row],[setor]],dim_custo_setor_horas!A:A,dim_custo_setor_horas!C:C)," ") -> 0 | H10: Rafael Souza | I10: Henrique Emiliano | J10: Henrique Emiliano | K10: Luiz Henrique | L10: Excelência Operacional - Filial | M10: 1 | N10: 46054 | O10: 46112 | P10: =Tabela2[[#This Row],[data_fim]]-Tabela2[[#This Row],[data_inicio]] -> 58 | Q10: 46054 | R10: 46113 | T10: 99 | V10: 288 | W10: =((Tabela2[[#This Row],[Horas economizadas anuais]] / 12) / 4) -> 6 | X10: =(_xlfn.XLOOKUP(Tabela2[[#This Row],[setor]],dim_custo_setor_horas!A:A,dim_custo_setor_horas!B:B))*Tabela2[[#This Row],[Horas economizadas anuais]] -> 13648.32 | Y10: =IF(Tabela2[[#This Row],[progresso_pct]]=100,Tabela2[[#This Row],[Retorno Previsto $]],0) -> 0 | Z10: =Tabela2[[#This Row],[duração_prev_dias]]*100 -> 5800 | AB10: =Tabela2[[#This Row],[capex]] -> 5800 | AC10: 800 | AD10: =IF(Tabela2[[#This Row],[progresso_pct]] = 100,IFERROR((Tabela2[[#This Row],[Retorno Previsto $]]-Tabela2[[#This Row],[spent_capex]])/Tabela2[[#This Row],[spent_capex]]," ")," ") | AE10: 10 | AF10: 3 | AG10: 3 | AH10: 3 | AI10: Aplicativo para centralização de indicadores Delp | AJ10: aprovar | AM10: =IFERROR(Tabela2[[#This Row],[Data Fim PMO]]-Tabela2[[#This Row],[Data Pedido PMO]],"") -> 0 | AP10: =IF(Tabela2[[#This Row],[Data Fim Prototipagem2]]=0," ",IFERROR(Tabela2[[#This Row],[Data Fim Prototipagem2]]-Tabela2[[#This Row],[Data Inicio Prototipagem]],"")) | AQ10: =Tabela2[[#This Row],[capex]] -> 5800
A11: PRJ-030 | B11: Melhorias Backoffice (BI -Suprimentos) | C11: BI & Eng. Dados | D11: Go Live | E11: =_xlfn.XLOOKUP(D11,validacao_lista!D:D,validacao_lista!E:E) -> 6 | F11: Validação, Testes e Otimização | G11: =IFERROR(_xlfn.XLOOKUP(Tabela2[[#This Row],[setor]],dim_custo_setor_horas!A:A,dim_custo_setor_horas!C:C)," ") -> 1 | H11: Luiz Castro | I11: Luiz Castro | J11: Marlon Tavares | K11: Rodrigo Nicácio | L11: Suprimentos - Filial | M11: 3 | N11: 46102 | O11: 46108 | P11: =Tabela2[[#This Row],[data_fim]]-Tabela2[[#This Row],[data_inicio]] -> 6 | T11: 40 | V11: 180 | W11: =((Tabela2[[#This Row],[Horas economizadas anuais]] / 12) / 4) -> 3.75 | X11: =(_xlfn.XLOOKUP(Tabela2[[#This Row],[setor]],dim_custo_setor_horas!A:A,dim_custo_setor_horas!B:B))*Tabela2[[#This Row],[Horas economizadas anuais]] -> 11435.4 | Y11: =IF(Tabela2[[#This Row],[progresso_pct]]=100,Tabela2[[#This Row],[Retorno Previsto $]],0) -> 0 | Z11: 500 | AD11: =IF(Tabela2[[#This Row],[progresso_pct]] = 100,IFERROR((Tabela2[[#This Row],[Retorno Previsto $]]-Tabela2[[#This Row],[spent_capex]])/Tabela2[[#This Row],[spent_capex]]," ")," ") | AF11: 3 | AG11: 1 | AH11: 1 | AI11: BI-Suprimentos | AJ11: aprovar | AM11: =IFERROR(Tabela2[[#This Row],[Data Fim PMO]]-Tabela2[[#This Row],[Data Pedido PMO]],"") -> 0 | AP11: =IF(Tabela2[[#This Row],[Data Fim Prototipagem2]]=0," ",IFERROR(Tabela2[[#This Row],[Data Fim Prototipagem2]]-Tabela2[[#This Row],[Data Inicio Prototipagem]],"")) | AQ11: 500
A12: PRJ-009 | B12: Portal de Notas Fiscais | C12: Software | D12: Go Live | E12: =_xlfn.XLOOKUP(D12,validacao_lista!D:D,validacao_lista!E:E) -> 6 | F12: Coleta de Dados e Preparação do Ambiente | G12: =IFERROR(_xlfn.XLOOKUP(Tabela2[[#This Row],[setor]],dim_custo_setor_horas!A:A,dim_custo_setor_horas!C:C)," ") -> 1 | H12: Rafael Souza | I12: Diego Bambirra | J12: Diego Bambirra | K12: Marcela | L12: Financeiro - Filial | M12: 3 | N12: 46054 | O12: 46113 | P12: =Tabela2[[#This Row],[data_fim]]-Tabela2[[#This Row],[data_inicio]] -> 59 | Q12: 46054 | T12: 30 | W12: =((Tabela2[[#This Row],[Horas economizadas anuais]] / 12) / 4) -> 0 | X12: =(_xlfn.XLOOKUP(Tabela2[[#This Row],[setor]],dim_custo_setor_horas!A:A,dim_custo_setor_horas!B:B))*Tabela2[[#This Row],[Horas economizadas anuais]] -> 0 | Y12: =IF(Tabela2[[#This Row],[progresso_pct]]=100,Tabela2[[#This Row],[Retorno Previsto $]],0) -> 0 | AD12: =IF(Tabela2[[#This Row],[progresso_pct]] = 100,IFERROR((Tabela2[[#This Row],[Retorno Previsto $]]-Tabela2[[#This Row],[spent_capex]])/Tabela2[[#This Row],[spent_capex]]," ")," ") | AF12: 5 | AG12: 3 | AH12: 3 | AI12: Portal centralizado para gestão de notas fiscais | AJ12: revisar | AK12: 46030 | AL12: 46085 | AM12: =IFERROR(Tabela2[[#This Row],[Data Fim PMO]]-Tabela2[[#This Row],[Data Pedido PMO]],"") -> 55 | AP12: =IF(Tabela2[[#This Row],[Data Fim Prototipagem2]]=0," ",IFERROR(Tabela2[[#This Row],[Data Fim Prototipagem2]]-Tabela2[[#This Row],[Data Inicio Prototipagem]],""))
A13: PRJ-015 | B13: BI - Controle SMDR | C13: BI & Eng. Dados | D13: Go Live | E13: =_xlfn.XLOOKUP(D13,validacao_lista!D:D,validacao_lista!E:E) -> 6 | F13: Entendimento e Planejamento | G13: =IFERROR(_xlfn.XLOOKUP(Tabela2[[#This Row],[setor]],dim_custo_setor_horas!A:A,dim_custo_setor_horas!C:C)," ") -> 0 | H13: Lucas Franca | I13: Lucas Franca | J13: Thais Felix | K13: Paulo Henrique | L13: Controle de Qualidade - Filial | M13: 3 | N13: 46085 | O13: 46106 | P13: =Tabela2[[#This Row],[data_fim]]-Tabela2[[#This Row],[data_inicio]] -> 21 | Q13: 46085 | R13: 46106 | T13: 100 | V13: 720 | W13: =((Tabela2[[#This Row],[Horas economizadas anuais]] / 12) / 4) -> 15 | X13: =(_xlfn.XLOOKUP(Tabela2[[#This Row],[setor]],dim_custo_setor_horas!A:A,dim_custo_setor_horas!B:B))*Tabela2[[#This Row],[Horas economizadas anuais]] -> 53719.2 | Y13: =IF(Tabela2[[#This Row],[progresso_pct]]=100,Tabela2[[#This Row],[Retorno Previsto $]],0) -> 53719.2 | Z13: 7500 | AB13: 7500 | AD13: =IF(Tabela2[[#This Row],[progresso_pct]] = 100,IFERROR((Tabela2[[#This Row],[Retorno Previsto $]]-Tabela2[[#This Row],[spent_capex]])/Tabela2[[#This Row],[spent_capex]]," ")," ") -> 6.16256 | AF13: 3 | AG13: 3 | AH13: 3 | AI13: Dashboard controle de qualidade CQ | AJ13: aprovar | AK13: 46085 | AL13: 46085 | AM13: =IFERROR(Tabela2[[#This Row],[Data Fim PMO]]-Tabela2[[#This Row],[Data Pedido PMO]],"") -> 0 | AP13: =IF(Tabela2[[#This Row],[Data Fim Prototipagem2]]=0," ",IFERROR(Tabela2[[#This Row],[Data Fim Prototipagem2]]-Tabela2[[#This Row],[Data Inicio Prototipagem]],"")) | AQ13: 7500
A14: PRJ-003 | B14: SOC | C14: Software | D14: Execução | E14: =_xlfn.XLOOKUP(D14,validacao_lista!D:D,validacao_lista!E:E) -> 5 | F14: Coleta de Dados e Preparação do Ambiente | G14: =IFERROR(_xlfn.XLOOKUP(Tabela2[[#This Row],[setor]],dim_custo_setor_horas!A:A,dim_custo_setor_horas!C:C)," ") -> 0 | H14: Lucas Franca | I14: Lucas Franca | J14: Wander Pereira | K14: Luciana | L14: SESMT – Segurança do Trabalho | M14: 3 | N14: 46023 | O14: 46172 | P14: =Tabela2[[#This Row],[data_fim]]-Tabela2[[#This Row],[data_inicio]] -> 149 | Q14: 46023 | T14: 40 | V14: =288*7 -> 2016 | W14: =((Tabela2[[#This Row],[Horas economizadas anuais]] / 12) / 4) -> 42 | X14: =(_xlfn.XLOOKUP(Tabela2[[#This Row],[setor]],dim_custo_setor_horas!A:A,dim_custo_setor_horas!B:B))*Tabela2[[#This Row],[Horas economizadas anuais]] -> 124528.32 | Y14: =IF(Tabela2[[#This Row],[progresso_pct]]=100,Tabela2[[#This Row],[Retorno Previsto $]],0) -> 0 | Z14: 103334.29 | AB14: 9000 | AC14: 0 | AD14: =IF(Tabela2[[#This Row],[progresso_pct]] = 100,IFERROR((Tabela2[[#This Row],[Retorno Previsto $]]-Tabela2[[#This Row],[spent_capex]])/Tabela2[[#This Row],[spent_capex]]," ")," ") | AE14: 14 | AF14: 5 | AG14: 3 | AH14: 3 | AI14: Sistema gestão SESMT / Saúde Ocupacional | AJ14: aprovar | AK14: 46031 | AL14: 46031 | AM14: =IFERROR(Tabela2[[#This Row],[Data Fim PMO]]-Tabela2[[#This Row],[Data Pedido PMO]],"") -> 0 | AP14: =IF(Tabela2[[#This Row],[Data Fim Prototipagem2]]=0," ",IFERROR(Tabela2[[#This Row],[Data Fim Prototipagem2]]-Tabela2[[#This Row],[Data Inicio Prototipagem]],""))
A15: PRJ-004 | B15: Apontamento Digital | C15: Software | D15: Execução | E15: =_xlfn.XLOOKUP(D15,validacao_lista!D:D,validacao_lista!E:E) -> 5 | F15: Entendimento e Planejamento | G15: =IFERROR(_xlfn.XLOOKUP(Tabela2[[#This Row],[setor]],dim_custo_setor_horas!A:A,dim_custo_setor_horas!C:C)," ") -> 0 | H15: Luiz Castro | I15: Luiz Castro | J15: Alisson | K15: Claudio M | L15: Planejamento PCP - Filial | M15: 3 | N15: 45992 | O15: 46356 | P15: =Tabela2[[#This Row],[data_fim]]-Tabela2[[#This Row],[data_inicio]] -> 364 | Q15: 45992 | T15: 35 | V15: 9200 | W15: =((Tabela2[[#This Row],[Horas economizadas anuais]] / 12) / 4) -> 191.66667 | X15: =(_xlfn.XLOOKUP(Tabela2[[#This Row],[setor]],dim_custo_setor_horas!A:A,dim_custo_setor_horas!B:B))*Tabela2[[#This Row],[Horas economizadas anuais]] -> 601404 | Y15: =IF(Tabela2[[#This Row],[progresso_pct]]=100,Tabela2[[#This Row],[Retorno Previsto $]],0) -> 0 | Z15: =129000+21900+3600+40417.18+100000+19900+96095.6+1310+26500 -> 438722.78 | AA15: 108000 | AB15: 47800 | AC15: 420 | AD15: =IF(Tabela2[[#This Row],[progresso_pct]] = 100,IFERROR((Tabela2[[#This Row],[Retorno Previsto $]]-Tabela2[[#This Row],[spent_capex]])/Tabela2[[#This Row],[spent_capex]]," ")," ") | AE15: 16 | AF15: 5 | AG15: 5 | AH15: 5 | AI15: Apontamento digital linha SKA - Fábrica | AJ15: aprovar | AK15: 46041 | AL15: 46041 | AM15: =IFERROR(Tabela2[[#This Row],[Data Fim PMO]]-Tabela2[[#This Row],[Data Pedido PMO]],"") -> 0 | AP15: =IF(Tabela2[[#This Row],[Data Fim Prototipagem2]]=0," ",IFERROR(Tabela2[[#This Row],[Data Fim Prototipagem2]]-Tabela2[[#This Row],[Data Inicio Prototipagem]],""))
A16: PRJ-005 | B16: Data Lake DELP | C16: Software | D16: Execução | E16: =_xlfn.XLOOKUP(D16,validacao_lista!D:D,validacao_lista!E:E) -> 5 | F16: Coleta de Dados e Preparação do Ambiente | G16: =IFERROR(_xlfn.XLOOKUP(Tabela2[[#This Row],[setor]],dim_custo_setor_horas!A:A,dim_custo_setor_horas!C:C)," ") -> 0 | H16: Henrique Emiliano | I16: Henrique Emiliano | J16: Henrique Emiliano | K16: Luiz Henrique | L16: Gerência da Produção - Filial | M16: 1 | N16: 46054 | O16: 46188 | P16: =Tabela2[[#This Row],[data_fim]]-Tabela2[[#This Row],[data_inicio]] -> 134 | Q16: 46054 | T16: 5 | U16: CÁLCULO ROI: 7,5% de economia de horas diárias de análise e compilação de dados por analistas e engenheiros. 0,075 *6 HORAS DIA = 45 min = 180 HORAS/ANO PESSOA. Considerando 30 pessoas na Delp que analisam e compilam dados. 180 horas pessoa * 30 pessoas = 5400 horas | V16: 10 | W16: =((Tabela2[[#This Row],[Horas economizadas anuais]] / 12) / 4) -> 0.20833333 | X16: =(_xlfn.XLOOKUP(Tabela2[[#This Row],[setor]],dim_custo_setor_horas!A:A,dim_custo_setor_horas!B:B))*Tabela2[[#This Row],[Horas economizadas anuais]] -> 1702.1 | Y16: =IF(Tabela2[[#This Row],[progresso_pct]]=100,Tabela2[[#This Row],[Retorno Previsto $]],0) -> 0 | Z16: 328265.18 | AA16: 18176.52 | AB16: 0 | AC16: 0 | AD16: =IF(Tabela2[[#This Row],[progresso_pct]] = 100,IFERROR((Tabela2[[#This Row],[Retorno Previsto $]]-Tabela2[[#This Row],[spent_capex]])/Tabela2[[#This Row],[spent_capex]]," ")," ") | AE16: 18 | AF16: 5 | AG16: 5 | AH16: 5 | AI16: Plataforma centralizada de dados DELP | AJ16: aprovar | AK16: 46029 | AL16: 46031 | AM16: =IFERROR(Tabela2[[#This Row],[Data Fim PMO]]-Tabela2[[#This Row],[Data Pedido PMO]],"") -> 2 | AP16: =IF(Tabela2[[#This Row],[Data Fim Prototipagem2]]=0," ",IFERROR(Tabela2[[#This Row],[Data Fim Prototipagem2]]-Tabela2[[#This Row],[Data Inicio Prototipagem]],""))
A17: PRJ-006 | B17: Sistema Stratws One | C17: Software | D17: Execução | E17: =_xlfn.XLOOKUP(D17,validacao_lista!D:D,validacao_lista!E:E) -> 5 | F17: Coleta de Dados e Preparação do Ambiente | G17: =IFERROR(_xlfn.XLOOKUP(Tabela2[[#This Row],[setor]],dim_custo_setor_horas!A:A,dim_custo_setor_horas!C:C)," ") -> 0 | H17: Rafael Souza | I17: Rafael Souza | J17: Iara | K17: Luiz Henrique | L17: Excelência Operacional - Filial | M17: 3 | N17: 46054 | O17: 46171 | P17: =Tabela2[[#This Row],[data_fim]]-Tabela2[[#This Row],[data_inicio]] -> 117 | Q17: 46054 | T17: 5 | V17: 2500 | W17: =((Tabela2[[#This Row],[Horas economizadas anuais]] / 12) / 4) -> 52.083333 | X17: =(_xlfn.XLOOKUP(Tabela2[[#This Row],[setor]],dim_custo_setor_horas!A:A,dim_custo_setor_horas!B:B))*Tabela2[[#This Row],[Horas economizadas anuais]] -> 118475 | Y17: =IF(Tabela2[[#This Row],[progresso_pct]]=100,Tabela2[[#This Row],[Retorno Previsto $]],0) -> 0 | Z17: 13200 | AA17: 98004 | AB17: 0 | AC17: 0 | AD17: =IF(Tabela2[[#This Row],[progresso_pct]] = 100,IFERROR((Tabela2[[#This Row],[Retorno Previsto $]]-Tabela2[[#This Row],[spent_capex]])/Tabela2[[#This Row],[spent_capex]]," ")," ") | AE17: 24 | AF17: 3 | AG17: 3 | AH17: 3 | AI17: Implantação sistema gestão estratégica Stratws One | AJ17: revisar | AK17: 46031 | AL17: 46032 | AM17: =IFERROR(Tabela2[[#This Row],[Data Fim PMO]]-Tabela2[[#This Row],[Data Pedido PMO]],"") -> 1 | AP17: =IF(Tabela2[[#This Row],[Data Fim Prototipagem2]]=0," ",IFERROR(Tabela2[[#This Row],[Data Fim Prototipagem2]]-Tabela2[[#This Row],[Data Inicio Prototipagem]],""))
A18: PRJ-010 | B18: Sistema Multi-Agêntico Delp | C18: IA | D18: Execução | E18: =_xlfn.XLOOKUP(D18,validacao_lista!D:D,validacao_lista!E:E) -> 5 | F18: Coleta de Dados e Preparação do Ambiente | G18: =IFERROR(_xlfn.XLOOKUP(Tabela2[[#This Row],[setor]],dim_custo_setor_horas!A:A,dim_custo_setor_horas!C:C)," ") -> 1 | H18: Henrique Emiliano | I18: Henrique Emiliano | J18: Diego Bambirra | K18: Jonatas Henrique | L18: Engenharia de Aplicação e Vendas | M18: 5 | N18: 46113 | O18: 46174 | P18: =Tabela2[[#This Row],[data_fim]]-Tabela2[[#This Row],[data_inicio]] -> 61 | T18: 0 | V18: 720 | W18: =((Tabela2[[#This Row],[Horas economizadas anuais]] / 12) / 4) -> 15 | X18: =(_xlfn.XLOOKUP(Tabela2[[#This Row],[setor]],dim_custo_setor_horas!A:A,dim_custo_setor_horas!B:B))*Tabela2[[#This Row],[Horas economizadas anuais]] -> 85629.6 | Y18: =IF(Tabela2[[#This Row],[progresso_pct]]=100,Tabela2[[#This Row],[Retorno Previsto $]],0) -> 0 | AD18: =IF(Tabela2[[#This Row],[progresso_pct]] = 100,IFERROR((Tabela2[[#This Row],[Retorno Previsto $]]-Tabela2[[#This Row],[spent_capex]])/Tabela2[[#This Row],[spent_capex]]," ")," ") | AF18: 5 | AG18: 3 | AH18: 5 | AI18: Agente GPT suporte ao sistema Kaizeka | AJ18: revisar | AK18: 46030 | AL18: 46085 | AM18: =IFERROR(Tabela2[[#This Row],[Data Fim PMO]]-Tabela2[[#This Row],[Data Pedido PMO]],"") -> 55 | AP18: =IF(Tabela2[[#This Row],[Data Fim Prototipagem2]]=0," ",IFERROR(Tabela2[[#This Row],[Data Fim Prototipagem2]]-Tabela2[[#This Row],[Data Inicio Prototipagem]],""))
A19: PRJ-032 | B19: Sala Tech NID | C19: Geral | D19: Encerrado | E19: =_xlfn.XLOOKUP(D19,validacao_lista!D:D,validacao_lista!E:E) -> 8 | F19: Implantação e Monitoramento | G19: =IFERROR(_xlfn.XLOOKUP(Tabela2[[#This Row],[setor]],dim_custo_setor_horas!A:A,dim_custo_setor_horas!C:C)," ") -> 0 | H19: Rafael Souza | I19: Rafael Souza | J19: Iara | K19: Luiz Henrique | L19: Excelência Operacional - Filial | M19: 3 | N19: 46054 | O19: 46127 | P19: =Tabela2[[#This Row],[data_fim]]-Tabela2[[#This Row],[data_inicio]] -> 73 | Q19: 46054 | R19: 46127 | T19: 100 | V19: 1 | W19: =((Tabela2[[#This Row],[Horas economizadas anuais]] / 12) / 4) -> 0.020833333 | X19: =(_xlfn.XLOOKUP(Tabela2[[#This Row],[setor]],dim_custo_setor_horas!A:A,dim_custo_setor_horas!B:B))*Tabela2[[#This Row],[Horas economizadas anuais]] -> 47.39 | Y19: =IF(Tabela2[[#This Row],[progresso_pct]]=100,Tabela2[[#This Row],[Retorno Previsto $]],0) -> 47.39 | Z19: 80000 | AB19: 70000 | AC19: 0 | AD19: =IF(Tabela2[[#This Row],[progresso_pct]] = 100,IFERROR((Tabela2[[#This Row],[Retorno Previsto $]]-Tabela2[[#This Row],[spent_capex]])/Tabela2[[#This Row],[spent_capex]]," ")," ") -> -0.999323 | AE19: 24 | AF19: 3 | AG19: 3 | AH19: 3 | AI19: Construção SALA NID | AJ19: revisar | AM19: =IFERROR(Tabela2[[#This Row],[Data Fim PMO]]-Tabela2[[#This Row],[Data Pedido PMO]],"") -> 0 | AP19: =IF(Tabela2[[#This Row],[Data Fim Prototipagem2]]=0," ",IFERROR(Tabela2[[#This Row],[Data Fim Prototipagem2]]-Tabela2[[#This Row],[Data Inicio Prototipagem]],""))
A20: PRJ-034 | B20: Calibre Analytics Metrologia | C20: BI & Eng. Dados | D20: Planejamento | E20: =_xlfn.XLOOKUP(D20,validacao_lista!D:D,validacao_lista!E:E) -> 4 | F20: Entendimento e Planejamento | G20: =IFERROR(_xlfn.XLOOKUP(Tabela2[[#This Row],[setor]],dim_custo_setor_horas!A:A,dim_custo_setor_horas!C:C)," ") -> 0 | H20: Lucas Franca | I20: Lucas Franca | J20: Maksimilian Reis | K20: Paulo Henrique | L20: Controle de Qualidade - Filial | M20: 3 | N20: 46105 | O20: 46164 | P20: =Tabela2[[#This Row],[data_fim]]-Tabela2[[#This Row],[data_inicio]] -> 59 | Q20: 46105 | T20: 5 | V20: 384 | W20: =((Tabela2[[#This Row],[Horas economizadas anuais]] / 12) / 4) -> 8 | X20: =(_xlfn.XLOOKUP(Tabela2[[#This Row],[setor]],dim_custo_setor_horas!A:A,dim_custo_setor_horas!B:B))*Tabela2[[#This Row],[Horas economizadas anuais]] -> 28650.24 | Y20: =IF(Tabela2[[#This Row],[progresso_pct]]=100,Tabela2[[#This Row],[Retorno Previsto $]],0) -> 0 | Z20: 10000 | AD20: =IF(Tabela2[[#This Row],[progresso_pct]] = 100,IFERROR((Tabela2[[#This Row],[Retorno Previsto $]]-Tabela2[[#This Row],[spent_capex]])/Tabela2[[#This Row],[spent_capex]]," ")," ") | AF20: 3 | AG20: 3 | AH20: 3 | AI20: BI Calibre Analytics Metrologia | AJ20: aprovar | AK20: 46105 | AL20: 46106 | AM20: =IFERROR(Tabela2[[#This Row],[Data Fim PMO]]-Tabela2[[#This Row],[Data Pedido PMO]],"") -> 1 | AP20: =IF(Tabela2[[#This Row],[Data Fim Prototipagem2]]=0," ",IFERROR(Tabela2[[#This Row],[Data Fim Prototipagem2]]-Tabela2[[#This Row],[Data Inicio Prototipagem]],"")) | AQ20: 10000
A21: PRJ-023 | B21: Gestão de Custos Usinagem | C21: Automações RPA | D21: Prototipagem/BC | E21: =_xlfn.XLOOKUP(D21,validacao_lista!D:D,validacao_lista!E:E) -> 3 | F21: Coleta de Dados e Preparação do Ambiente | G21: =IFERROR(_xlfn.XLOOKUP(Tabela2[[#This Row],[setor]],dim_custo_setor_horas!A:A,dim_custo_setor_horas!C:C)," ") -> 0 | H21: Luiz Castro | I21: Luiz Castro | J21: Alex Fernando | K21: Rodrigo Alves | L21: Apoio Usinagem e Montagem Mecânica | M21: 5 | N21: 46076 | O21: 46135 | P21: =Tabela2[[#This Row],[data_fim]]-Tabela2[[#This Row],[data_inicio]] -> 59 | Q21: 46076 | T21: 2 | U21: CÁLCULO ROI: economia de horas diárias de análise e compilação de dados. 0,4 *6 HORAS DIA = 2,4 horas = 576 HORAS/ANO PESSOA. | V21: 576 | W21: =((Tabela2[[#This Row],[Horas economizadas anuais]] / 12) / 4) -> 12 | X21: =(_xlfn.XLOOKUP(Tabela2[[#This Row],[setor]],dim_custo_setor_horas!A:A,dim_custo_setor_horas!B:B))*Tabela2[[#This Row],[Horas economizadas anuais]] -> 40573.44 | Y21: =IF(Tabela2[[#This Row],[progresso_pct]]=100,Tabela2[[#This Row],[Retorno Previsto $]],0) -> 0 | Z21: =Tabela2[[#This Row],[duração_prev_dias]]*100 -> 5900 | AD21: =IF(Tabela2[[#This Row],[progresso_pct]] = 100,IFERROR((Tabela2[[#This Row],[Retorno Previsto $]]-Tabela2[[#This Row],[spent_capex]])/Tabela2[[#This Row],[spent_capex]]," ")," ") | AF21: 3 | AG21: 3 | AH21: 3 | AI21: Gestão de custos da área de usinagem | AJ21: revisar | AL21: - | AM21: =IFERROR(Tabela2[[#This Row],[Data Fim PMO]]-Tabela2[[#This Row],[Data Pedido PMO]],"") | AP21: =IF(Tabela2[[#This Row],[Data Fim Prototipagem2]]=0," ",IFERROR(Tabela2[[#This Row],[Data Fim Prototipagem2]]-Tabela2[[#This Row],[Data Inicio Prototipagem]],""))
A22: PRJ-007 | B22: Databook Digital Fase 2 | C22: Software | D22: Prototipagem/BC | E22: =_xlfn.XLOOKUP(D22,validacao_lista!D:D,validacao_lista!E:E) -> 3 | F22: Seleção de fornecedor | G22: =IFERROR(_xlfn.XLOOKUP(Tabela2[[#This Row],[setor]],dim_custo_setor_horas!A:A,dim_custo_setor_horas!C:C)," ") -> 0 | H22: Lucas Franca | I22: Henrique Emiliano | J22: Islam | K22: Paulo Henrique | L22: Controle de Qualidade - Filial | M22: 3 | N22: 45992 | O22: 46266 | P22: =Tabela2[[#This Row],[data_fim]]-Tabela2[[#This Row],[data_inicio]] -> 274 | Q22: 45992 | T22: 5 | V22: 9200 | W22: =((Tabela2[[#This Row],[Horas economizadas anuais]] / 12) / 4) -> 191.66667 | X22: =(_xlfn.XLOOKUP(Tabela2[[#This Row],[setor]],dim_custo_setor_horas!A:A,dim_custo_setor_horas!B:B))*Tabela2[[#This Row],[Horas economizadas anuais]] -> 686412 | Y22: =IF(Tabela2[[#This Row],[progresso_pct]]=100,Tabela2[[#This Row],[Retorno Previsto $]],0) -> 0 | AD22: =IF(Tabela2[[#This Row],[progresso_pct]] = 100,IFERROR((Tabela2[[#This Row],[Retorno Previsto $]]-Tabela2[[#This Row],[spent_capex]])/Tabela2[[#This Row],[spent_capex]]," ")," ") | AE22: 15 | AF22: 5 | AG22: 5 | AH22: 5 | AI22: Segunda fase do databook digital CQ | AJ22: aprovar | AK22: 46035 | AL22: 46057 | AM22: =IFERROR(Tabela2[[#This Row],[Data Fim PMO]]-Tabela2[[#This Row],[Data Pedido PMO]],"") -> 22 | AP22: =IF(Tabela2[[#This Row],[Data Fim Prototipagem2]]=0," ",IFERROR(Tabela2[[#This Row],[Data Fim Prototipagem2]]-Tabela2[[#This Row],[Data Inicio Prototipagem]],""))
A23: PRJ-014 | B23: Reformulação Delp Ideia | C23: BI & Eng. Dados | D23: Prototipagem/BC | E23: =_xlfn.XLOOKUP(D23,validacao_lista!D:D,validacao_lista!E:E) -> 3 | F23: Entendimento e Planejamento | G23: =IFERROR(_xlfn.XLOOKUP(Tabela2[[#This Row],[setor]],dim_custo_setor_horas!A:A,dim_custo_setor_horas!C:C)," ") -> 0 | H23: Lucas Franca | I23: Lucas Franca | J23: Emanuelle | K23: Luiz Henrique | L23: Excelência Operacional - Filial | M23: 5 | N23: 46062 | O23: 46142 | P23: =Tabela2[[#This Row],[data_fim]]-Tabela2[[#This Row],[data_inicio]] -> 80 | Q23: 46062 | T23: 8 | V23: 720 | W23: =((Tabela2[[#This Row],[Horas economizadas anuais]] / 12) / 4) -> 15 | X23: =(_xlfn.XLOOKUP(Tabela2[[#This Row],[setor]],dim_custo_setor_horas!A:A,dim_custo_setor_horas!B:B))*Tabela2[[#This Row],[Horas economizadas anuais]] -> 34120.8 | Y23: =IF(Tabela2[[#This Row],[progresso_pct]]=100,Tabela2[[#This Row],[Retorno Previsto $]],0) -> 0 | Z23: 10000 | AD23: =IF(Tabela2[[#This Row],[progresso_pct]] = 100,IFERROR((Tabela2[[#This Row],[Retorno Previsto $]]-Tabela2[[#This Row],[spent_capex]])/Tabela2[[#This Row],[spent_capex]]," ")," ") | AF23: 1 | AG23: 5 | AH23: 1 | AI23: Reformulação automação programa Delp Ideia | AJ23: revisar | AK23: 46037 | AL23: 46085 | AM23: =IFERROR(Tabela2[[#This Row],[Data Fim PMO]]-Tabela2[[#This Row],[Data Pedido PMO]],"") -> 48 | AP23: =IF(Tabela2[[#This Row],[Data Fim Prototipagem2]]=0," ",IFERROR(Tabela2[[#This Row],[Data Fim Prototipagem2]]-Tabela2[[#This Row],[Data Inicio Prototipagem]],"")) | AQ23: 10000
A24: PRJ-036 | B24: Automatização Adm Fábrica | C24: Automações RPA | D24: Prototipagem/BC | E24: =_xlfn.XLOOKUP(D24,validacao_lista!D:D,validacao_lista!E:E) -> 3 | F24: Entendimento e Planejamento | G24: =IFERROR(_xlfn.XLOOKUP(Tabela2[[#This Row],[setor]],dim_custo_setor_horas!A:A,dim_custo_setor_horas!C:C)," ") -> 0 | H24: Luiz Castro | I24: Luiz Castro | J24: Kênia Sousa | K24: Claudio M | L24: Planejamento PCP - Filial | M24: 3 | N24: 46118 | O24: 46178 | P24: =Tabela2[[#This Row],[data_fim]]-Tabela2[[#This Row],[data_inicio]] -> 60 | T24: 0 | V24: 416 | W24: =((Tabela2[[#This Row],[Horas economizadas anuais]] / 12) / 4) -> 8.6666667 | X24: =(_xlfn.XLOOKUP(Tabela2[[#This Row],[setor]],dim_custo_setor_horas!A:A,dim_custo_setor_horas!B:B))*Tabela2[[#This Row],[Horas economizadas anuais]] -> 27193.92 | Y24: =IF(Tabela2[[#This Row],[progresso_pct]]=100,Tabela2[[#This Row],[Retorno Previsto $]],0) -> 0 | Z24: 5000 | AD24: =IF(Tabela2[[#This Row],[progresso_pct]] = 100,IFERROR((Tabela2[[#This Row],[Retorno Previsto $]]-Tabela2[[#This Row],[spent_capex]])/Tabela2[[#This Row],[spent_capex]]," ")," ") | AF24: 3 | AG24: 3 | AH24: 3 | AI24: Automação do fluxo de | AM24: =IFERROR(Tabela2[[#This Row],[Data Fim PMO]]-Tabela2[[#This Row],[Data Pedido PMO]],"") -> 0 | AP24: =IF(Tabela2[[#This Row],[Data Fim Prototipagem2]]=0," ",IFERROR(Tabela2[[#This Row],[Data Fim Prototipagem2]]-Tabela2[[#This Row],[Data Inicio Prototipagem]],""))
A25: PRJ-038 | B25: Automatização - Delp Field | C25: Automações RPA | D25: Prototipagem/BC | E25: =_xlfn.XLOOKUP(D25,validacao_lista!D:D,validacao_lista!E:E) -> 3 | F25: Entendimento e Planejamento | G25: =IFERROR(_xlfn.XLOOKUP(Tabela2[[#This Row],[setor]],dim_custo_setor_horas!A:A,dim_custo_setor_horas!C:C)," ") -> 0 | H25: Henrique Emiliano | I25: Henrique Emiliano | J25: Igor Oliveira | K25: Marcos Lima | L25: Field Service | M25: 3 | N25: 46118 | O25: 46178 | P25: =Tabela2[[#This Row],[data_fim]]-Tabela2[[#This Row],[data_inicio]] -> 60 | T25: 0 | V25: 416 | W25: =((Tabela2[[#This Row],[Horas economizadas anuais]] / 12) / 4) -> 8.6666667 | X25: =(_xlfn.XLOOKUP(Tabela2[[#This Row],[setor]],dim_custo_setor_horas!A:A,dim_custo_setor_horas!B:B))*Tabela2[[#This Row],[Horas economizadas anuais]] -> 52170.56 | Y25: =IF(Tabela2[[#This Row],[progresso_pct]]=100,Tabela2[[#This Row],[Retorno Previsto $]],0) -> 0 | Z25: 5000 | AD25: =IF(Tabela2[[#This Row],[progresso_pct]] = 100,IFERROR((Tabela2[[#This Row],[Retorno Previsto $]]-Tabela2[[#This Row],[spent_capex]])/Tabela2[[#This Row],[spent_capex]]," ")," ") | AF25: 3 | AG25: 3 | AH25: 3 | AI25: Mapeamento e automatização do setor Delp Field | AJ25: aprovar | AK25: 46118 | AL25: 46178 | AM25: =IFERROR(Tabela2[[#This Row],[Data Fim PMO]]-Tabela2[[#This Row],[Data Pedido PMO]],"") -> 60 | AP25: =IF(Tabela2[[#This Row],[Data Fim Prototipagem2]]=0," ",IFERROR(Tabela2[[#This Row],[Data Fim Prototipagem2]]-Tabela2[[#This Row],[Data Inicio Prototipagem]],""))
A26: PRJ-028 | B26: Layout Fabril Automático | C26: Software | D26: Backlog | E26: =_xlfn.XLOOKUP(D26,validacao_lista!D:D,validacao_lista!E:E) -> 1 | F26: Seleção de fornecedor | G26: =IFERROR(_xlfn.XLOOKUP(Tabela2[[#This Row],[setor]],dim_custo_setor_horas!A:A,dim_custo_setor_horas!C:C)," ") -> 0 | H26: Luiz Castro | I26: Luiz Castro | J26: Carlos Meinberg | K26: Claudio M | L26: Planejamento PCP - Filial | M26: 3 | N26: 46113 | O26: 46174 | P26: =Tabela2[[#This Row],[data_fim]]-Tabela2[[#This Row],[data_inicio]] -> 61 | T26: 10 | W26: =((Tabela2[[#This Row],[Horas economizadas anuais]] / 12) / 4) -> 0 | X26: =(_xlfn.XLOOKUP(Tabela2[[#This Row],[setor]],dim_custo_setor_horas!A:A,dim_custo_setor_horas!B:B))*Tabela2[[#This Row],[Horas economizadas anuais]] -> 0 | Y26: =IF(Tabela2[[#This Row],[progresso_pct]]=100,Tabela2[[#This Row],[Retorno Previsto $]],0) -> 0 | AD26: =IF(Tabela2[[#This Row],[progresso_pct]] = 100,IFERROR((Tabela2[[#This Row],[Retorno Previsto $]]-Tabela2[[#This Row],[spent_capex]])/Tabela2[[#This Row],[spent_capex]]," ")," ") | AE26: 16 | AF26: 5 | AG26: 3 | AH26: 3 | AI26: Layout Fabril Automático | AJ26: aprovar | AL26: - | AM26: =IFERROR(Tabela2[[#This Row],[Data Fim PMO]]-Tabela2[[#This Row],[Data Pedido PMO]],"") | AP26: =IF(Tabela2[[#This Row],[Data Fim Prototipagem2]]=0," ",IFERROR(Tabela2[[#This Row],[Data Fim Prototipagem2]]-Tabela2[[#This Row],[Data Inicio Prototipagem]],""))
A27: PRJ-027 | B27: BI Controle Projetos - Fase - Pasta 36 | C27: BI & Eng. Dados | D27: Backlog | E27: =_xlfn.XLOOKUP(D27,validacao_lista!D:D,validacao_lista!E:E) -> 1 | F27: Entendimento e Planejamento | G27: =IFERROR(_xlfn.XLOOKUP(Tabela2[[#This Row],[setor]],dim_custo_setor_horas!A:A,dim_custo_setor_horas!C:C)," ") -> 0 | H27: Luiz Castro | I27: Luiz Castro | J27: Carlos Meinberg | K27: Claudio M | L27: Planejamento PCP - Filial | M27: 3 | N27: 46082 | O27: 46143 | P27: =Tabela2[[#This Row],[data_fim]]-Tabela2[[#This Row],[data_inicio]] -> 61 | T27: 0 | W27: =((Tabela2[[#This Row],[Horas economizadas anuais]] / 12) / 4) -> 0 | X27: =(_xlfn.XLOOKUP(Tabela2[[#This Row],[setor]],dim_custo_setor_horas!A:A,dim_custo_setor_horas!B:B))*Tabela2[[#This Row],[Horas economizadas anuais]] -> 0 | Y27: =IF(Tabela2[[#This Row],[progresso_pct]]=100,Tabela2[[#This Row],[Retorno Previsto $]],0) -> 0 | AD27: =IF(Tabela2[[#This Row],[progresso_pct]] = 100,IFERROR((Tabela2[[#This Row],[Retorno Previsto $]]-Tabela2[[#This Row],[spent_capex]])/Tabela2[[#This Row],[spent_capex]]," ")," ") | AF27: 3 | AG27: 3 | AH27: 3 | AI27: BI controle interno de projetos - Pasta 36 | AJ27: revisar | AK27: 46034 | AL27: 46085 | AM27: =IFERROR(Tabela2[[#This Row],[Data Fim PMO]]-Tabela2[[#This Row],[Data Pedido PMO]],"") -> 51 | AP27: =IF(Tabela2[[#This Row],[Data Fim Prototipagem2]]=0," ",IFERROR(Tabela2[[#This Row],[Data Fim Prototipagem2]]-Tabela2[[#This Row],[Data Inicio Prototipagem]],""))
A28: PRJ-008 | B28: Orçabot - Agente de Cotações | C28: IA | D28: Backlog | E28: =_xlfn.XLOOKUP(D28,validacao_lista!D:D,validacao_lista!E:E) -> 1 | G28: =IFERROR(_xlfn.XLOOKUP(Tabela2[[#This Row],[setor]],dim_custo_setor_horas!A:A,dim_custo_setor_horas!C:C)," ") -> 1 | H28: Rafael Souza | I28: Henrique Emiliano | J28: Darkson | K28: Jonatas | L28: Comercial Mooring | M28: 3 | P28: =Tabela2[[#This Row],[data_fim]]-Tabela2[[#This Row],[data_inicio]] -> 0 | T28: 0 | W28: =((Tabela2[[#This Row],[Horas economizadas anuais]] / 12) / 4) -> 0 | X28: =(_xlfn.XLOOKUP(Tabela2[[#This Row],[setor]],dim_custo_setor_horas!A:A,dim_custo_setor_horas!B:B))*Tabela2[[#This Row],[Horas economizadas anuais]] -> 0 | Y28: =IF(Tabela2[[#This Row],[progresso_pct]]=100,Tabela2[[#This Row],[Retorno Previsto $]],0) -> 0 | AD28: =IF(Tabela2[[#This Row],[progresso_pct]] = 100,IFERROR((Tabela2[[#This Row],[Retorno Previsto $]]-Tabela2[[#This Row],[spent_capex]])/Tabela2[[#This Row],[spent_capex]]," ")," ") | AF28: 3 | AG28: 5 | AH28: 3 | AI28: Agente IA para automação de cotações | AJ28: aprovar | AK28: 46031 | AL28: 46085 | AM28: =IFERROR(Tabela2[[#This Row],[Data Fim PMO]]-Tabela2[[#This Row],[Data Pedido PMO]],"") -> 54 | AP28: =IF(Tabela2[[#This Row],[Data Fim Prototipagem2]]=0," ",IFERROR(Tabela2[[#This Row],[Data Fim Prototipagem2]]-Tabela2[[#This Row],[Data Inicio Prototipagem]],""))
A29: PRJ-011 | B29: Plataforma Gestão de Mudanças | C29: Automações RPA | D29: Backlog | E29: =_xlfn.XLOOKUP(D29,validacao_lista!D:D,validacao_lista!E:E) -> 1 | G29: =IFERROR(_xlfn.XLOOKUP(Tabela2[[#This Row],[setor]],dim_custo_setor_horas!A:A,dim_custo_setor_horas!C:C)," ") -> 1 | H29: Rafael Souza | I29: Girlesio | J29: Girlésio | K29: Luiz Henrique | L29: SGQ - Filial | M29: 5 | P29: =Tabela2[[#This Row],[data_fim]]-Tabela2[[#This Row],[data_inicio]] -> 0 | T29: 0 | W29: =((Tabela2[[#This Row],[Horas economizadas anuais]] / 12) / 4) -> 0 | X29: =(_xlfn.XLOOKUP(Tabela2[[#This Row],[setor]],dim_custo_setor_horas!A:A,dim_custo_setor_horas!B:B))*Tabela2[[#This Row],[Horas economizadas anuais]] -> 0 | Y29: =IF(Tabela2[[#This Row],[progresso_pct]]=100,Tabela2[[#This Row],[Retorno Previsto $]],0) -> 0 | AD29: =IF(Tabela2[[#This Row],[progresso_pct]] = 100,IFERROR((Tabela2[[#This Row],[Retorno Previsto $]]-Tabela2[[#This Row],[spent_capex]])/Tabela2[[#This Row],[spent_capex]]," ")," ") | AF29: 1 | AG29: 3 | AH29: 1 | AI29: Plataforma para gerenciamento de gestão de mudanças | AJ29: revisar | AK29: 46030 | AL29: 46085 | AM29: =IFERROR(Tabela2[[#This Row],[Data Fim PMO]]-Tabela2[[#This Row],[Data Pedido PMO]],"") -> 55 | AP29: =IF(Tabela2[[#This Row],[Data Fim Prototipagem2]]=0," ",IFERROR(Tabela2[[#This Row],[Data Fim Prototipagem2]]-Tabela2[[#This Row],[Data Inicio Prototipagem]],""))
A30: PRJ-013 | B30: Projeto Carregamento Fabril | C30: BI & Eng. Dados | D30: Backlog | E30: =_xlfn.XLOOKUP(D30,validacao_lista!D:D,validacao_lista!E:E) -> 1 | G30: =IFERROR(_xlfn.XLOOKUP(Tabela2[[#This Row],[setor]],dim_custo_setor_horas!A:A,dim_custo_setor_horas!C:C)," ") -> 0 | H30: Luiz Castro | I30: Luiz Castro | J30: Chistiane | K30: Claudio M | L30: Planejamento PCP - Filial | M30: 5 | P30: =Tabela2[[#This Row],[data_fim]]-Tabela2[[#This Row],[data_inicio]] -> 0 | T30: 0 | W30: =((Tabela2[[#This Row],[Horas economizadas anuais]] / 12) / 4) -> 0 | X30: =(_xlfn.XLOOKUP(Tabela2[[#This Row],[setor]],dim_custo_setor_horas!A:A,dim_custo_setor_horas!B:B))*Tabela2[[#This Row],[Horas economizadas anuais]] -> 0 | Y30: =IF(Tabela2[[#This Row],[progresso_pct]]=100,Tabela2[[#This Row],[Retorno Previsto $]],0) -> 0 | AD30: =IF(Tabela2[[#This Row],[progresso_pct]] = 100,IFERROR((Tabela2[[#This Row],[Retorno Previsto $]]-Tabela2[[#This Row],[spent_capex]])/Tabela2[[#This Row],[spent_capex]]," ")," ") | AF30: 5 | AG30: 5 | AH30: 3 | AI30: Dashboard detalhado de carregamento fabril | AJ30: revisar | AK30: 46034 | AL30: 46085 | AM30: =IFERROR(Tabela2[[#This Row],[Data Fim PMO]]-Tabela2[[#This Row],[Data Pedido PMO]],"") -> 51 | AP30: =IF(Tabela2[[#This Row],[Data Fim Prototipagem2]]=0," ",IFERROR(Tabela2[[#This Row],[Data Fim Prototipagem2]]-Tabela2[[#This Row],[Data Inicio Prototipagem]],""))
A31: PRJ-016 | B31: CIRO Automático | C31: Automações RPA | D31: Backlog | E31: =_xlfn.XLOOKUP(D31,validacao_lista!D:D,validacao_lista!E:E) -> 1 | G31: =IFERROR(_xlfn.XLOOKUP(Tabela2[[#This Row],[setor]],dim_custo_setor_horas!A:A,dim_custo_setor_horas!C:C)," ") -> 0 | H31: Lucas Franca | I31: Lucas Rodrigues | J31: Lucas Rodrigues | K31: Paulo Henrique | L31: Controle de Qualidade - Filial | M31: 5 | P31: =Tabela2[[#This Row],[data_fim]]-Tabela2[[#This Row],[data_inicio]] -> 0 | T31: 0 | W31: =((Tabela2[[#This Row],[Horas economizadas anuais]] / 12) / 4) -> 0 | X31: =(_xlfn.XLOOKUP(Tabela2[[#This Row],[setor]],dim_custo_setor_horas!A:A,dim_custo_setor_horas!B:B))*Tabela2[[#This Row],[Horas economizadas anuais]] -> 0 | Y31: =IF(Tabela2[[#This Row],[progresso_pct]]=100,Tabela2[[#This Row],[Retorno Previsto $]],0) -> 0 | AD31: =IF(Tabela2[[#This Row],[progresso_pct]] = 100,IFERROR((Tabela2[[#This Row],[Retorno Previsto $]]-Tabela2[[#This Row],[spent_capex]])/Tabela2[[#This Row],[spent_capex]]," ")," ") | AF31: 1 | AG31: 3 | AH31: 1 | AI31: Automação do processo CIRO para CQ | AJ31: revisar | AK31: 46035 | AL31: 46085 | AM31: =IFERROR(Tabela2[[#This Row],[Data Fim PMO]]-Tabela2[[#This Row],[Data Pedido PMO]],"") -> 50 | AP31: =IF(Tabela2[[#This Row],[Data Fim Prototipagem2]]=0," ",IFERROR(Tabela2[[#This Row],[Data Fim Prototipagem2]]-Tabela2[[#This Row],[Data Inicio Prototipagem]],""))
A32: PRJ-017 | B32: CDS Automático | C32: Automações RPA | D32: Backlog | E32: =_xlfn.XLOOKUP(D32,validacao_lista!D:D,validacao_lista!E:E) -> 1 | G32: =IFERROR(_xlfn.XLOOKUP(Tabela2[[#This Row],[setor]],dim_custo_setor_horas!A:A,dim_custo_setor_horas!C:C)," ") -> 0 | H32: Lucas Franca | I32: Lucas Rodrigues | J32: Lucas Rodrigues | K32: Paulo Henrique | L32: Controle de Qualidade - Filial | M32: 5 | P32: =Tabela2[[#This Row],[data_fim]]-Tabela2[[#This Row],[data_inicio]] -> 0 | T32: 0 | W32: =((Tabela2[[#This Row],[Horas economizadas anuais]] / 12) / 4) -> 0 | X32: =(_xlfn.XLOOKUP(Tabela2[[#This Row],[setor]],dim_custo_setor_horas!A:A,dim_custo_setor_horas!B:B))*Tabela2[[#This Row],[Horas economizadas anuais]] -> 0 | Y32: =IF(Tabela2[[#This Row],[progresso_pct]]=100,Tabela2[[#This Row],[Retorno Previsto $]],0) -> 0 | AD32: =IF(Tabela2[[#This Row],[progresso_pct]] = 100,IFERROR((Tabela2[[#This Row],[Retorno Previsto $]]-Tabela2[[#This Row],[spent_capex]])/Tabela2[[#This Row],[spent_capex]]," ")," ") | AF32: 1 | AG32: 3 | AH32: 1 | AI32: Automação do processo CDS para CQ | AJ32: revisar | AK32: 46035 | AL32: 46085 | AM32: =IFERROR(Tabela2[[#This Row],[Data Fim PMO]]-Tabela2[[#This Row],[Data Pedido PMO]],"") -> 50 | AP32: =IF(Tabela2[[#This Row],[Data Fim Prototipagem2]]=0," ",IFERROR(Tabela2[[#This Row],[Data Fim Prototipagem2]]-Tabela2[[#This Row],[Data Inicio Prototipagem]],""))
A33: PRJ-018 | B33: Reformulação Estrutura HH/Ton | C33: Melhoria ERP | D33: Backlog | E33: =_xlfn.XLOOKUP(D33,validacao_lista!D:D,validacao_lista!E:E) -> 1 | G33: =IFERROR(_xlfn.XLOOKUP(Tabela2[[#This Row],[setor]],dim_custo_setor_horas!A:A,dim_custo_setor_horas!C:C)," ") -> 0 | H33: Luiz Castro | I33: Luiz Castro | J33: Leandro | K33: Wagner | L33: Engenharia Industrial de Caldeiraria - Filial | M33: 5 | P33: =Tabela2[[#This Row],[data_fim]]-Tabela2[[#This Row],[data_inicio]] -> 0 | T33: 0 | W33: =((Tabela2[[#This Row],[Horas economizadas anuais]] / 12) / 4) -> 0 | X33: =(_xlfn.XLOOKUP(Tabela2[[#This Row],[setor]],dim_custo_setor_horas!A:A,dim_custo_setor_horas!B:B))*Tabela2[[#This Row],[Horas economizadas anuais]] -> 0 | Y33: =IF(Tabela2[[#This Row],[progresso_pct]]=100,Tabela2[[#This Row],[Retorno Previsto $]],0) -> 0 | AD33: =IF(Tabela2[[#This Row],[progresso_pct]] = 100,IFERROR((Tabela2[[#This Row],[Retorno Previsto $]]-Tabela2[[#This Row],[spent_capex]])/Tabela2[[#This Row],[spent_capex]]," ")," ") | AF33: 5 | AG33: 5 | AH33: 5 | AI33: Reformulação estrutura apontamento HH/ton ERP | AJ33: revisar | AK33: 46034 | AL33: 46085 | AM33: =IFERROR(Tabela2[[#This Row],[Data Fim PMO]]-Tabela2[[#This Row],[Data Pedido PMO]],"") -> 51 | AP33: =IF(Tabela2[[#This Row],[Data Fim Prototipagem2]]=0," ",IFERROR(Tabela2[[#This Row],[Data Fim Prototipagem2]]-Tabela2[[#This Row],[Data Inicio Prototipagem]],""))
A34: PRJ-019 | B34: Reserva de Material Engenharia | C34: Melhoria ERP | D34: Backlog | E34: =_xlfn.XLOOKUP(D34,validacao_lista!D:D,validacao_lista!E:E) -> 1 | G34: =IFERROR(_xlfn.XLOOKUP(Tabela2[[#This Row],[setor]],dim_custo_setor_horas!A:A,dim_custo_setor_horas!C:C)," ") -> 0 | H34: Luiz Castro | I34: Luiz Castro | J34: Leandro | K34: Wagner | L34: Engenharia Industrial de Caldeiraria - Filial | M34: 3 | P34: =Tabela2[[#This Row],[data_fim]]-Tabela2[[#This Row],[data_inicio]] -> 0 | T34: 0 | W34: =((Tabela2[[#This Row],[Horas economizadas anuais]] / 12) / 4) -> 0 | X34: =(_xlfn.XLOOKUP(Tabela2[[#This Row],[setor]],dim_custo_setor_horas!A:A,dim_custo_setor_horas!B:B))*Tabela2[[#This Row],[Horas economizadas anuais]] -> 0 | Y34: =IF(Tabela2[[#This Row],[progresso_pct]]=100,Tabela2[[#This Row],[Retorno Previsto $]],0) -> 0 | AD34: =IF(Tabela2[[#This Row],[progresso_pct]] = 100,IFERROR((Tabela2[[#This Row],[Retorno Previsto $]]-Tabela2[[#This Row],[spent_capex]])/Tabela2[[#This Row],[spent_capex]]," ")," ") | AF34: 3 | AG34: 3 | AH34: 3 | AI34: Reserva de material de projetos de engenharia | AJ34: revisar | AK34: 46034 | AL34: 46085 | AM34: =IFERROR(Tabela2[[#This Row],[Data Fim PMO]]-Tabela2[[#This Row],[Data Pedido PMO]],"") -> 51 | AP34: =IF(Tabela2[[#This Row],[Data Fim Prototipagem2]]=0," ",IFERROR(Tabela2[[#This Row],[Data Fim Prototipagem2]]-Tabela2[[#This Row],[Data Inicio Prototipagem]],""))
A35: PRJ-020 | B35: BSC Integrado Fase 3 | C35: BI & Eng. Dados | D35: Backlog | E35: =_xlfn.XLOOKUP(D35,validacao_lista!D:D,validacao_lista!E:E) -> 1 | G35: =IFERROR(_xlfn.XLOOKUP(Tabela2[[#This Row],[setor]],dim_custo_setor_horas!A:A,dim_custo_setor_horas!C:C)," ") -> 1 | H35: Rafael Souza | I35: Rafael Souza | J35: Bruno Lima | K35: Reinaldo De Paoli | L35: Gerência de Projetos - Filial | M35: 3 | P35: =Tabela2[[#This Row],[data_fim]]-Tabela2[[#This Row],[data_inicio]] -> 0 | T35: 0 | W35: =((Tabela2[[#This Row],[Horas economizadas anuais]] / 12) / 4) -> 0 | X35: =(_xlfn.XLOOKUP(Tabela2[[#This Row],[setor]],dim_custo_setor_horas!A:A,dim_custo_setor_horas!B:B))*Tabela2[[#This Row],[Horas economizadas anuais]] -> 0 | Y35: =IF(Tabela2[[#This Row],[progresso_pct]]=100,Tabela2[[#This Row],[Retorno Previsto $]],0) -> 0 | AD35: =IF(Tabela2[[#This Row],[progresso_pct]] = 100,IFERROR((Tabela2[[#This Row],[Retorno Previsto $]]-Tabela2[[#This Row],[spent_capex]])/Tabela2[[#This Row],[spent_capex]]," ")," ") | AF35: 5 | AG35: 5 | AH35: 5 | AI35: Terceira fase BSC integrado - Gerência de Projeto | AJ35: aprovar | AK35: - | AL35: - | AM35: =IFERROR(Tabela2[[#This Row],[Data Fim PMO]]-Tabela2[[#This Row],[Data Pedido PMO]],"") | AP35: =IF(Tabela2[[#This Row],[Data Fim Prototipagem2]]=0," ",IFERROR(Tabela2[[#This Row],[Data Fim Prototipagem2]]-Tabela2[[#This Row],[Data Inicio Prototipagem]],""))
A36: PRJ-021 | B36: Percepto - Monitoramento Processos | C36: Software | D36: Backlog | E36: =_xlfn.XLOOKUP(D36,validacao_lista!D:D,validacao_lista!E:E) -> 1 | G36: =IFERROR(_xlfn.XLOOKUP(Tabela2[[#This Row],[setor]],dim_custo_setor_horas!A:A,dim_custo_setor_horas!C:C)," ") -> 0 | H36: Rafael Souza | I36: Rafael Souza | J36: Henrique Emiliano | K36: Luiz Henrique | L36: Excelência Operacional - Filial | M36: 3 | P36: =Tabela2[[#This Row],[data_fim]]-Tabela2[[#This Row],[data_inicio]] -> 0 | T36: 0 | W36: =((Tabela2[[#This Row],[Horas economizadas anuais]] / 12) / 4) -> 0 | X36: =(_xlfn.XLOOKUP(Tabela2[[#This Row],[setor]],dim_custo_setor_horas!A:A,dim_custo_setor_horas!B:B))*Tabela2[[#This Row],[Horas economizadas anuais]] -> 0 | Y36: =IF(Tabela2[[#This Row],[progresso_pct]]=100,Tabela2[[#This Row],[Retorno Previsto $]],0) -> 0 | AD36: =IF(Tabela2[[#This Row],[progresso_pct]] = 100,IFERROR((Tabela2[[#This Row],[Retorno Previsto $]]-Tabela2[[#This Row],[spent_capex]])/Tabela2[[#This Row],[spent_capex]]," ")," ") | AF36: 3 | AG36: 3 | AH36: 3 | AI36: Monitoramento inteligente de processos produtivos | AJ36: aprovar | AK36: - | AL36: - | AM36: =IFERROR(Tabela2[[#This Row],[Data Fim PMO]]-Tabela2[[#This Row],[Data Pedido PMO]],"") | AP36: =IF(Tabela2[[#This Row],[Data Fim Prototipagem2]]=0," ",IFERROR(Tabela2[[#This Row],[Data Fim Prototipagem2]]-Tabela2[[#This Row],[Data Inicio Prototipagem]],""))
A37: PRJ-022 | B37: Controle Contratos Manufatura Fluig | C37: Melhoria ERP | D37: Backlog | E37: =_xlfn.XLOOKUP(D37,validacao_lista!D:D,validacao_lista!E:E) -> 1 | G37: =IFERROR(_xlfn.XLOOKUP(Tabela2[[#This Row],[setor]],dim_custo_setor_horas!A:A,dim_custo_setor_horas!C:C)," ") -> 0 | H37: Luiz Castro | I37: Luiz Castro | J37: Carlos Meinberg | K37: Claudio M | L37: Planejamento PCP - Filial | M37: 5 | P37: =Tabela2[[#This Row],[data_fim]]-Tabela2[[#This Row],[data_inicio]] -> 0 | T37: 0 | W37: =((Tabela2[[#This Row],[Horas economizadas anuais]] / 12) / 4) -> 0 | X37: =(_xlfn.XLOOKUP(Tabela2[[#This Row],[setor]],dim_custo_setor_horas!A:A,dim_custo_setor_horas!B:B))*Tabela2[[#This Row],[Horas economizadas anuais]] -> 0 | Y37: =IF(Tabela2[[#This Row],[progresso_pct]]=100,Tabela2[[#This Row],[Retorno Previsto $]],0) -> 0 | AD37: =IF(Tabela2[[#This Row],[progresso_pct]] = 100,IFERROR((Tabela2[[#This Row],[Retorno Previsto $]]-Tabela2[[#This Row],[spent_capex]])/Tabela2[[#This Row],[spent_capex]]," ")," ") | AF37: 3 | AG37: 3 | AH37: 3 | AI37: Controle contratos manufatura no Fluig/RM | AJ37: revisar | AK37: - | AL37: - | AM37: =IFERROR(Tabela2[[#This Row],[Data Fim PMO]]-Tabela2[[#This Row],[Data Pedido PMO]],"") | AP37: =IF(Tabela2[[#This Row],[Data Fim Prototipagem2]]=0," ",IFERROR(Tabela2[[#This Row],[Data Fim Prototipagem2]]-Tabela2[[#This Row],[Data Inicio Prototipagem]],""))
A38: PRJ-039 | B38: RPA - Relatório Automatizado de Ultassom | C38: Automações RPA | D38: Encerrado | E38: =_xlfn.XLOOKUP(D38,validacao_lista!D:D,validacao_lista!E:E) -> 8 | F38: Implantação e Monitoramento | G38: =IFERROR(_xlfn.XLOOKUP(Tabela2[[#This Row],[setor]],dim_custo_setor_horas!A:A,dim_custo_setor_horas!C:C)," ") -> 0 | H38: Lucas Franca | I38: Lucas Franca | J38: Warley Teotonio | K38: Paulo Henrique | L38: Controle de Qualidade - Filial | M38: 3 | N38: 46114 | O38: 46118 | P38: =Tabela2[[#This Row],[data_fim]]-Tabela2[[#This Row],[data_inicio]] -> 4 | Q38: 46114 | R38: 46118 | T38: 100 | V38: 192 | W38: =((Tabela2[[#This Row],[Horas economizadas anuais]] / 12) / 4) -> 4 | X38: =(_xlfn.XLOOKUP(Tabela2[[#This Row],[setor]],dim_custo_setor_horas!A:A,dim_custo_setor_horas!B:B))*Tabela2[[#This Row],[Horas economizadas anuais]] -> 14325.12 | Y38: =IF(Tabela2[[#This Row],[progresso_pct]]=100,Tabela2[[#This Row],[Retorno Previsto $]],0) -> 14325.12 | Z38: 1000 | AB38: 1000 | AD38: =IF(Tabela2[[#This Row],[progresso_pct]] = 100,IFERROR((Tabela2[[#This Row],[Retorno Previsto $]]-Tabela2[[#This Row],[spent_capex]])/Tabela2[[#This Row],[spent_capex]]," ")," ") -> 13.32512 | AF38: 3 | AG38: 3 | AH38: 1 | AI38: Relatório Automatizado de Ultassom | AJ38: aprovar | AM38: =IFERROR(Tabela2[[#This Row],[Data Fim PMO]]-Tabela2[[#This Row],[Data Pedido PMO]],"") -> 0 | AP38: =IF(Tabela2[[#This Row],[Data Fim Prototipagem2]]=0," ",IFERROR(Tabela2[[#This Row],[Data Fim Prototipagem2]]-Tabela2[[#This Row],[Data Inicio Prototipagem]],"")) | AQ38: 1000
A39: PRJ-040 | B39: Dashboard de conformidade Dimensional | C39: BI & Eng. Dados | D39: Go Live | E39: =_xlfn.XLOOKUP(D39,validacao_lista!D:D,validacao_lista!E:E) -> 6 | F39: Validação, Testes e Otimização | G39: =IFERROR(_xlfn.XLOOKUP(Tabela2[[#This Row],[setor]],dim_custo_setor_horas!A:A,dim_custo_setor_horas!C:C)," ") -> 0 | H39: Lucas Franca | I39: Lucas Franca | J39: Warley Teotonio | K39: Paulo Henrique | L39: Controle de Qualidade - Filial | M39: 3 | N39: 46120 | O39: 46122 | P39: =Tabela2[[#This Row],[data_fim]]-Tabela2[[#This Row],[data_inicio]] -> 2 | Q39: 46120 | R39: 46122 | T39: 99 | V39: 720 | W39: =((Tabela2[[#This Row],[Horas economizadas anuais]] / 12) / 4) -> 15 | X39: =(_xlfn.XLOOKUP(Tabela2[[#This Row],[setor]],dim_custo_setor_horas!A:A,dim_custo_setor_horas!B:B))*Tabela2[[#This Row],[Horas economizadas anuais]] -> 53719.2 | Y39: =IF(Tabela2[[#This Row],[progresso_pct]]=100,Tabela2[[#This Row],[Retorno Previsto $]],0) -> 0 | Z39: 800 | AB39: 750 | AD39: =IF(Tabela2[[#This Row],[progresso_pct]] = 100,IFERROR((Tabela2[[#This Row],[Retorno Previsto $]]-Tabela2[[#This Row],[spent_capex]])/Tabela2[[#This Row],[spent_capex]]," ")," ") | AF39: 3 | AG39: 3 | AH39: 1 | AI39: Controle de desempenho de caldeireiro | AJ39: aprovar | AM39: =IFERROR(Tabela2[[#This Row],[Data Fim PMO]]-Tabela2[[#This Row],[Data Pedido PMO]],"") -> 0 | AP39: =IF(Tabela2[[#This Row],[Data Fim Prototipagem2]]=0," ",IFERROR(Tabela2[[#This Row],[Data Fim Prototipagem2]]-Tabela2[[#This Row],[Data Inicio Prototipagem]],"")) | AQ39: 800
A40: PRJ-041 | B40: Melhorias Backoffice (BI - Almoxarifado) | C40: BI & Eng. Dados | D40: Encerrado | E40: =_xlfn.XLOOKUP(D40,validacao_lista!D:D,validacao_lista!E:E) -> 8 | F40: Implantação e Monitoramento | G40: =IFERROR(_xlfn.XLOOKUP(Tabela2[[#This Row],[setor]],dim_custo_setor_horas!A:A,dim_custo_setor_horas!C:C)," ") -> 1 | H40: Luiz Castro | I40: Luiz Castro | J40: Dayane Rocha | K40: Rodrigo Nicácio | L40: Almoxarifado - Filial | M40: 3 | N40: 46119 | O40: 46129 | P40: =Tabela2[[#This Row],[data_fim]]-Tabela2[[#This Row],[data_inicio]] -> 10 | Q40: 46119 | R40: 46129 | T40: 100 | V40: 96 | W40: =((Tabela2[[#This Row],[Horas economizadas anuais]] / 12) / 4) -> 2 | X40: =(_xlfn.XLOOKUP(Tabela2[[#This Row],[setor]],dim_custo_setor_horas!A:A,dim_custo_setor_horas!B:B))*Tabela2[[#This Row],[Horas economizadas anuais]] -> 5018.88 | Y40: =IF(Tabela2[[#This Row],[progresso_pct]]=100,Tabela2[[#This Row],[Retorno Previsto $]],0) -> 5018.88 | Z40: 1300 | AB40: 1300 | AD40: =IF(Tabela2[[#This Row],[progresso_pct]] = 100,IFERROR((Tabela2[[#This Row],[Retorno Previsto $]]-Tabela2[[#This Row],[spent_capex]])/Tabela2[[#This Row],[spent_capex]]," ")," ") -> 2.8606769 | AI40: BI controle SLA de pendências | AK40: 46119 | AL40: 46119 | AM40: =IFERROR(Tabela2[[#This Row],[Data Fim PMO]]-Tabela2[[#This Row],[Data Pedido PMO]],"") -> 0 | AN40: 46119 | AO40: 46119 | AP40: =IF(Tabela2[[#This Row],[Data Fim Prototipagem2]]=0," ",IFERROR(Tabela2[[#This Row],[Data Fim Prototipagem2]]-Tabela2[[#This Row],[Data Inicio Prototipagem]],"")) -> 0 | AQ40: 1300
W41: =((Tabela2[[#This Row],[Horas economizadas anuais]] / 12) / 4) -> 0 | X41: =(_xlfn.XLOOKUP(Tabela2[[#This Row],[setor]],dim_custo_setor_horas!A:A,dim_custo_setor_horas!B:B))*Tabela2[[#This Row],[Horas economizadas anuais]] -> 0 | Y41: =IF(Tabela2[[#This Row],[progresso_pct]]=100,Tabela2[[#This Row],[Retorno Previsto $]],0) -> 0 | AD41: =IF(Tabela2[[#This Row],[progresso_pct]] = 100,IFERROR((Tabela2[[#This Row],[Retorno Previsto $]]-Tabela2[[#This Row],[spent_capex]])/Tabela2[[#This Row],[spent_capex]]," ")," ") | AM41: =IFERROR(Tabela2[[#This Row],[Data Fim PMO]]-Tabela2[[#This Row],[Data Pedido PMO]],"") -> 0 | AP41: =IF(Tabela2[[#This Row],[Data Fim Prototipagem2]]=0," ",IFERROR(Tabela2[[#This Row],[Data Fim Prototipagem2]]-Tabela2[[#This Row],[Data Inicio Prototipagem]],""))
W42: =((Tabela2[[#This Row],[Horas economizadas anuais]] / 12) / 4) -> 0 | X42: =(_xlfn.XLOOKUP(Tabela2[[#This Row],[setor]],dim_custo_setor_horas!A:A,dim_custo_setor_horas!B:B))*Tabela2[[#This Row],[Horas economizadas anuais]] -> 0 | Y42: =IF(Tabela2[[#This Row],[progresso_pct]]=100,Tabela2[[#This Row],[Retorno Previsto $]],0) -> 0 | AD42: =IF(Tabela2[[#This Row],[progresso_pct]] = 100,IFERROR((Tabela2[[#This Row],[Retorno Previsto $]]-Tabela2[[#This Row],[spent_capex]])/Tabela2[[#This Row],[spent_capex]]," ")," ") | AM42: =IFERROR(Tabela2[[#This Row],[Data Fim PMO]]-Tabela2[[#This Row],[Data Pedido PMO]],"") -> 0 | AP42: =IF(Tabela2[[#This Row],[Data Fim Prototipagem2]]=0," ",IFERROR(Tabela2[[#This Row],[Data Fim Prototipagem2]]-Tabela2[[#This Row],[Data Inicio Prototipagem]],""))
W43: =((Tabela2[[#This Row],[Horas economizadas anuais]] / 12) / 4) -> 0 | X43: =(_xlfn.XLOOKUP(Tabela2[[#This Row],[setor]],dim_custo_setor_horas!A:A,dim_custo_setor_horas!B:B))*Tabela2[[#This Row],[Horas economizadas anuais]] -> 0 | Y43: =IF(Tabela2[[#This Row],[progresso_pct]]=100,Tabela2[[#This Row],[Retorno Previsto $]],0) -> 0 | AD43: =IF(Tabela2[[#This Row],[progresso_pct]] = 100,IFERROR((Tabela2[[#This Row],[Retorno Previsto $]]-Tabela2[[#This Row],[spent_capex]])/Tabela2[[#This Row],[spent_capex]]," ")," ") | AM43: =IFERROR(Tabela2[[#This Row],[Data Fim PMO]]-Tabela2[[#This Row],[Data Pedido PMO]],"") -> 0 | AP43: =IF(Tabela2[[#This Row],[Data Fim Prototipagem2]]=0," ",IFERROR(Tabela2[[#This Row],[Data Fim Prototipagem2]]-Tabela2[[#This Row],[Data Inicio Prototipagem]],""))
W44: =((Tabela2[[#This Row],[Horas economizadas anuais]] / 12) / 4) -> 0 | X44: =(_xlfn.XLOOKUP(Tabela2[[#This Row],[setor]],dim_custo_setor_horas!A:A,dim_custo_setor_horas!B:B))*Tabela2[[#This Row],[Horas economizadas anuais]] -> 0 | Y44: =IF(Tabela2[[#This Row],[progresso_pct]]=100,Tabela2[[#This Row],[Retorno Previsto $]],0) -> 0 | AD44: =IF(Tabela2[[#This Row],[progresso_pct]] = 100,IFERROR((Tabela2[[#This Row],[Retorno Previsto $]]-Tabela2[[#This Row],[spent_capex]])/Tabela2[[#This Row],[spent_capex]]," ")," ") | AM44: =IFERROR(Tabela2[[#This Row],[Data Fim PMO]]-Tabela2[[#This Row],[Data Pedido PMO]],"") -> 0 | AP44: =IF(Tabela2[[#This Row],[Data Fim Prototipagem2]]=0," ",IFERROR(Tabela2[[#This Row],[Data Fim Prototipagem2]]-Tabela2[[#This Row],[Data Inicio Prototipagem]],""))
W45: =((Tabela2[[#This Row],[Horas economizadas anuais]] / 12) / 4) -> 0 | X45: =(_xlfn.XLOOKUP(Tabela2[[#This Row],[setor]],dim_custo_setor_horas!A:A,dim_custo_setor_horas!B:B))*Tabela2[[#This Row],[Horas economizadas anuais]] -> 0 | Y45: =IF(Tabela2[[#This Row],[progresso_pct]]=100,Tabela2[[#This Row],[Retorno Previsto $]],0) -> 0 | AD45: =IF(Tabela2[[#This Row],[progresso_pct]] = 100,IFERROR((Tabela2[[#This Row],[Retorno Previsto $]]-Tabela2[[#This Row],[spent_capex]])/Tabela2[[#This Row],[spent_capex]]," ")," ") | AM45: =IFERROR(Tabela2[[#This Row],[Data Fim PMO]]-Tabela2[[#This Row],[Data Pedido PMO]],"") -> 0 | AP45: =IF(Tabela2[[#This Row],[Data Fim Prototipagem2]]=0," ",IFERROR(Tabela2[[#This Row],[Data Fim Prototipagem2]]-Tabela2[[#This Row],[Data Inicio Prototipagem]],""))
W46: =((Tabela2[[#This Row],[Horas economizadas anuais]] / 12) / 4) -> 0 | X46: =(_xlfn.XLOOKUP(Tabela2[[#This Row],[setor]],dim_custo_setor_horas!A:A,dim_custo_setor_horas!B:B))*Tabela2[[#This Row],[Horas economizadas anuais]] -> 0 | Y46: =IF(Tabela2[[#This Row],[progresso_pct]]=100,Tabela2[[#This Row],[Retorno Previsto $]],0) -> 0 | AD46: =IF(Tabela2[[#This Row],[progresso_pct]] = 100,IFERROR((Tabela2[[#This Row],[Retorno Previsto $]]-Tabela2[[#This Row],[spent_capex]])/Tabela2[[#This Row],[spent_capex]]," ")," ") | AM46: =IFERROR(Tabela2[[#This Row],[Data Fim PMO]]-Tabela2[[#This Row],[Data Pedido PMO]],"") -> 0 | AP46: =IF(Tabela2[[#This Row],[Data Fim Prototipagem2]]=0," ",IFERROR(Tabela2[[#This Row],[Data Fim Prototipagem2]]-Tabela2[[#This Row],[Data Inicio Prototipagem]],""))
W47: =((Tabela2[[#This Row],[Horas economizadas anuais]] / 12) / 4) -> 0 | X47: =(_xlfn.XLOOKUP(Tabela2[[#This Row],[setor]],dim_custo_setor_horas!A:A,dim_custo_setor_horas!B:B))*Tabela2[[#This Row],[Horas economizadas anuais]] -> 0 | Y47: =IF(Tabela2[[#This Row],[progresso_pct]]=100,Tabela2[[#This Row],[Retorno Previsto $]],0) -> 0 | AD47: =IF(Tabela2[[#This Row],[progresso_pct]] = 100,IFERROR((Tabela2[[#This Row],[Retorno Previsto $]]-Tabela2[[#This Row],[spent_capex]])/Tabela2[[#This Row],[spent_capex]]," ")," ") | AM47: =IFERROR(Tabela2[[#This Row],[Data Fim PMO]]-Tabela2[[#This Row],[Data Pedido PMO]],"") -> 0 | AP47: =IF(Tabela2[[#This Row],[Data Fim Prototipagem2]]=0," ",IFERROR(Tabela2[[#This Row],[Data Fim Prototipagem2]]-Tabela2[[#This Row],[Data Inicio Prototipagem]],""))
W48: =((Tabela2[[#This Row],[Horas economizadas anuais]] / 12) / 4) -> 0 | X48: =(_xlfn.XLOOKUP(Tabela2[[#This Row],[setor]],dim_custo_setor_horas!A:A,dim_custo_setor_horas!B:B))*Tabela2[[#This Row],[Horas economizadas anuais]] -> 0 | Y48: =IF(Tabela2[[#This Row],[progresso_pct]]=100,Tabela2[[#This Row],[Retorno Previsto $]],0) -> 0 | AD48: =IF(Tabela2[[#This Row],[progresso_pct]] = 100,IFERROR((Tabela2[[#This Row],[Retorno Previsto $]]-Tabela2[[#This Row],[spent_capex]])/Tabela2[[#This Row],[spent_capex]]," ")," ") | AM48: =IFERROR(Tabela2[[#This Row],[Data Fim PMO]]-Tabela2[[#This Row],[Data Pedido PMO]],"") -> 0 | AP48: =IF(Tabela2[[#This Row],[Data Fim Prototipagem2]]=0," ",IFERROR(Tabela2[[#This Row],[Data Fim Prototipagem2]]-Tabela2[[#This Row],[Data Inicio Prototipagem]],""))
W49: =((Tabela2[[#This Row],[Horas economizadas anuais]] / 12) / 4) -> 0 | X49: =(_xlfn.XLOOKUP(Tabela2[[#This Row],[setor]],dim_custo_setor_horas!A:A,dim_custo_setor_horas!B:B))*Tabela2[[#This Row],[Horas economizadas anuais]] -> 0 | Y49: =IF(Tabela2[[#This Row],[progresso_pct]]=100,Tabela2[[#This Row],[Retorno Previsto $]],0) -> 0 | AD49: =IF(Tabela2[[#This Row],[progresso_pct]] = 100,IFERROR((Tabela2[[#This Row],[Retorno Previsto $]]-Tabela2[[#This Row],[spent_capex]])/Tabela2[[#This Row],[spent_capex]]," ")," ") | AM49: =IFERROR(Tabela2[[#This Row],[Data Fim PMO]]-Tabela2[[#This Row],[Data Pedido PMO]],"") -> 0 | AP49: =IF(Tabela2[[#This Row],[Data Fim Prototipagem2]]=0," ",IFERROR(Tabela2[[#This Row],[Data Fim Prototipagem2]]-Tabela2[[#This Row],[Data Inicio Prototipagem]],""))
W50: =((Tabela2[[#This Row],[Horas economizadas anuais]] / 12) / 4) -> 0 | X50: =(_xlfn.XLOOKUP(Tabela2[[#This Row],[setor]],dim_custo_setor_horas!A:A,dim_custo_setor_horas!B:B))*Tabela2[[#This Row],[Horas economizadas anuais]] -> 0 | Y50: =IF(Tabela2[[#This Row],[progresso_pct]]=100,Tabela2[[#This Row],[Retorno Previsto $]],0) -> 0 | AD50: =IF(Tabela2[[#This Row],[progresso_pct]] = 100,IFERROR((Tabela2[[#This Row],[Retorno Previsto $]]-Tabela2[[#This Row],[spent_capex]])/Tabela2[[#This Row],[spent_capex]]," ")," ") | AM50: =IFERROR(Tabela2[[#This Row],[Data Fim PMO]]-Tabela2[[#This Row],[Data Pedido PMO]],"") -> 0 | AP50: =IF(Tabela2[[#This Row],[Data Fim Prototipagem2]]=0," ",IFERROR(Tabela2[[#This Row],[Data Fim Prototipagem2]]-Tabela2[[#This Row],[Data Inicio Prototipagem]],""))
W51: =((Tabela2[[#This Row],[Horas economizadas anuais]] / 12) / 4) -> 0 | X51: =(_xlfn.XLOOKUP(Tabela2[[#This Row],[setor]],dim_custo_setor_horas!A:A,dim_custo_setor_horas!B:B))*Tabela2[[#This Row],[Horas economizadas anuais]] -> 0 | Y51: =IF(Tabela2[[#This Row],[progresso_pct]]=100,Tabela2[[#This Row],[Retorno Previsto $]],0) -> 0 | AD51: =IF(Tabela2[[#This Row],[progresso_pct]] = 100,IFERROR((Tabela2[[#This Row],[Retorno Previsto $]]-Tabela2[[#This Row],[spent_capex]])/Tabela2[[#This Row],[spent_capex]]," ")," ") | AM51: =IFERROR(Tabela2[[#This Row],[Data Fim PMO]]-Tabela2[[#This Row],[Data Pedido PMO]],"") -> 0 | AP51: =IF(Tabela2[[#This Row],[Data Fim Prototipagem2]]=0," ",IFERROR(Tabela2[[#This Row],[Data Fim Prototipagem2]]-Tabela2[[#This Row],[Data Inicio Prototipagem]],""))
W52: =((Tabela2[[#This Row],[Horas economizadas anuais]] / 12) / 4) -> 0 | X52: =(_xlfn.XLOOKUP(Tabela2[[#This Row],[setor]],dim_custo_setor_horas!A:A,dim_custo_setor_horas!B:B))*Tabela2[[#This Row],[Horas economizadas anuais]] -> 0 | Y52: =IF(Tabela2[[#This Row],[progresso_pct]]=100,Tabela2[[#This Row],[Retorno Previsto $]],0) -> 0 | AD52: =IF(Tabela2[[#This Row],[progresso_pct]] = 100,IFERROR((Tabela2[[#This Row],[Retorno Previsto $]]-Tabela2[[#This Row],[spent_capex]])/Tabela2[[#This Row],[spent_capex]]," ")," ") | AM52: =IFERROR(Tabela2[[#This Row],[Data Fim PMO]]-Tabela2[[#This Row],[Data Pedido PMO]],"") -> 0 | AP52: =IF(Tabela2[[#This Row],[Data Fim Prototipagem2]]=0," ",IFERROR(Tabela2[[#This Row],[Data Fim Prototipagem2]]-Tabela2[[#This Row],[Data Inicio Prototipagem]],""))
... W198: =((Tabela2[[#This Row],[Horas economizadas anuais]] / 12) / 4) -> 0 | X198: =(_xlfn.XLOOKUP(Tabela2[[#This Row],[setor]],dim_custo_setor_horas!A:A,dim_custo_setor_horas!B:B))*Tabela2[[#This Row],[Horas economizadas anuais]] -> 0 | Y198: =IF(Tabela2[[#This Row],[progresso_pct]]=100,Tabela2[[#This Row],[Retorno Previsto $]],0) -> 0 | AD198: =IF(Tabela2[[#This Row],[progresso_pct]] = 100,IFERROR((Tabela2[[#This Row],[Retorno Previsto $]]-Tabela2[[#This Row],[spent_capex]])/Tabela2[[#This Row],[spent_capex]]," ")," ") | AM198: =IFERROR(Tabela2[[#This Row],[Data Fim PMO]]-Tabela2[[#This Row],[Data Pedido PMO]],"") -> 0 | AP198: =IF(Tabela2[[#This Row],[Data Fim Prototipagem2]]=0," ",IFERROR(Tabela2[[#This Row],[Data Fim Prototipagem2]]-Tabela2[[#This Row],[Data Inicio Prototipagem]],""))

Sheet membros_nucleo
A1: id | B1: nome | C1: cargo | D1: setor | E1: squad | F1: is_active | G1: monthly_capacity_hours | H1: custo_hora | I1: data_entrada
A2: MBR-001 | B2: Henrique Emiliano | C2: Tech Lead | D2: NID | E2: IA | F2: 1 | G2: 128 | H2: 100 | I2: 45962
A3: MBR-002 | B3: Rafael Souza | C3: Product Owner / QA | D3: NID | E3: Software | F3: 1 | G3: 60 | H3: 100 | I3: 46023
A4: MBR-003 | B4: Lucas Franca | C4: Analista BP | D4: NID | E4: BI & Eng. Dados | F4: 1 | G4: 140 | H4: 100 | I4: 46054
A5: MBR-004 | B5: Luiz Castro | C5: Analista BP | D5: NID | E5: Automações RPA | F5: 1 | G5: 140 | H5: 100 | I5: 46054
A6: MBR-005 | B6: César | C6: Analista M1 | D6: NID | E6: Software | F6: 1 | G6: 100 | H6: 100 | I6: 46082

Sheet alocacoes
A1: id | B1: membro_id | C1: membro_nome | D1: projeto_id | E1: projeto_nome | F1: squad | G1: horas_por_semana | H1: data_inicio | I1: data_fim | J1: is_active
A2: ALO-002 | B2: =IFERROR(_xlfn.XLOOKUP(Tabela4[[#This Row],[membro_nome]],Tabela3[nome],Tabela3[id])," ") -> MBR-001 | C2: Henrique Emiliano | D2: =IFERROR(_xlfn.XLOOKUP(Tabela4[[#This Row],[projeto_nome]],projetos!B:B,projetos!A:A)," ") -> PRJ-001 | E2: BI People Analytics RH | F2: =IF(Tabela4[[#This Row],[projeto_nome]]=0," ",_xlfn.XLOOKUP(Tabela4[[#This Row],[projeto_nome]],projetos!B:B,projetos!C:C)) -> BI & Eng. Dados | G2: =_xlfn.XLOOKUP(F2,dim_custo_setor_horas!$E$1:$E$8,dim_custo_setor_horas!$F$1:$F$8," ") -> 20 | H2: =IF(Tabela4[[#This Row],[projeto_nome]]=0," ",_xlfn.XLOOKUP(Tabela4[[#This Row],[projeto_id]],projetos!A:A,projetos!N:N," ")) -> 45992 | I2: =_xlfn.XLOOKUP(Tabela4[[#This Row],[projeto_id]],projetos!A:A,projetos!O:O," ") -> 46112 | J2: 1
A3: ALO-005 | B3: =IFERROR(_xlfn.XLOOKUP(Tabela4[[#This Row],[membro_nome]],Tabela3[nome],Tabela3[id])," ") -> MBR-001 | C3: Henrique Emiliano | D3: =IFERROR(_xlfn.XLOOKUP(Tabela4[[#This Row],[projeto_nome]],projetos!B:B,projetos!A:A)," ") -> PRJ-002 | E3: BI SGQ | F3: =IF(Tabela4[[#This Row],[projeto_nome]]=0," ",_xlfn.XLOOKUP(Tabela4[[#This Row],[projeto_nome]],projetos!B:B,projetos!C:C)) -> BI & Eng. Dados | G3: 15 | H3: =IF(Tabela4[[#This Row],[projeto_nome]]=0," ",_xlfn.XLOOKUP(Tabela4[[#This Row],[projeto_id]],projetos!A:A,projetos!N:N," ")) -> 46054 | I3: =_xlfn.XLOOKUP(Tabela4[[#This Row],[projeto_id]],projetos!A:A,projetos!O:O," ") -> 46112 | J3: 1
A4: ALO-007 | B4: =IFERROR(_xlfn.XLOOKUP(Tabela4[[#This Row],[membro_nome]],Tabela3[nome],Tabela3[id])," ") -> MBR-001 | C4: Henrique Emiliano | D4: =IFERROR(_xlfn.XLOOKUP(Tabela4[[#This Row],[projeto_nome]],projetos!B:B,projetos!A:A)," ") -> PRJ-005 | E4: Data Lake DELP | F4: =IF(Tabela4[[#This Row],[projeto_nome]]=0," ",_xlfn.XLOOKUP(Tabela4[[#This Row],[projeto_nome]],projetos!B:B,projetos!C:C)) -> Software | G4: =_xlfn.XLOOKUP(F4,dim_custo_setor_horas!$E$1:$E$8,dim_custo_setor_horas!$F$1:$F$8," ") -> 6 | H4: =IF(Tabela4[[#This Row],[projeto_nome]]=0," ",_xlfn.XLOOKUP(Tabela4[[#This Row],[projeto_id]],projetos!A:A,projetos!N:N," ")) -> 46054 | I4: =_xlfn.XLOOKUP(Tabela4[[#This Row],[projeto_id]],projetos!A:A,projetos!O:O," ") -> 46188 | J4: 1
A5: ALO-011 | B5: =IFERROR(_xlfn.XLOOKUP(Tabela4[[#This Row],[membro_nome]],Tabela3[nome],Tabela3[id])," ") -> MBR-001 | C5: Henrique Emiliano | D5: =IFERROR(_xlfn.XLOOKUP(Tabela4[[#This Row],[projeto_nome]],projetos!B:B,projetos!A:A)," ") -> PRJ-007 | E5: Databook Digital Fase 2 | F5: =IF(Tabela4[[#This Row],[projeto_nome]]=0," ",_xlfn.XLOOKUP(Tabela4[[#This Row],[projeto_nome]],projetos!B:B,projetos!C:C)) -> Software | G5: =_xlfn.XLOOKUP(F5,dim_custo_setor_horas!$E$1:$E$8,dim_custo_setor_horas!$F$1:$F$8," ") -> 6 | H5: =IF(Tabela4[[#This Row],[projeto_nome]]=0," ",_xlfn.XLOOKUP(Tabela4[[#This Row],[projeto_id]],projetos!A:A,projetos!N:N," ")) -> 45992 | I5: =_xlfn.XLOOKUP(Tabela4[[#This Row],[projeto_id]],projetos!A:A,projetos!O:O," ") -> 46266 | J5: 1
A6: ALO-019 | B6: =IFERROR(_xlfn.XLOOKUP(Tabela4[[#This Row],[membro_nome]],Tabela3[nome],Tabela3[id])," ") -> MBR-001 | C6: Henrique Emiliano | D6: =IFERROR(_xlfn.XLOOKUP(Tabela4[[#This Row],[projeto_nome]],projetos!B:B,projetos!A:A)," ") | E6: KaizekaGPT | F6: =IF(Tabela4[[#This Row],[projeto_nome]]=0," ",_xlfn.XLOOKUP(Tabela4[[#This Row],[projeto_nome]],projetos!B:B,projetos!C:C)) -> #N/A | G6: =_xlfn.XLOOKUP(F6,dim_custo_setor_horas!$E$1:$E$8,dim_custo_setor_horas!$F$1:$F$8," ") -> #N/A | H6: =IF(Tabela4[[#This Row],[projeto_nome]]=0," ",_xlfn.XLOOKUP(Tabela4[[#This Row],[projeto_id]],projetos!A:A,projetos!N:N," ")) | I6: =_xlfn.XLOOKUP(Tabela4[[#This Row],[projeto_id]],projetos!A:A,projetos!O:O," ") | J6: 1
A7: ALO-020 | B7: =IFERROR(_xlfn.XLOOKUP(Tabela4[[#This Row],[membro_nome]],Tabela3[nome],Tabela3[id])," ") -> MBR-001 | C7: Henrique Emiliano | D7: =IFERROR(_xlfn.XLOOKUP(Tabela4[[#This Row],[projeto_nome]],projetos!B:B,projetos!A:A)," ") -> PRJ-038 | E7: Automatização - Delp Field | F7: =IF(Tabela4[[#This Row],[projeto_nome]]=0," ",_xlfn.XLOOKUP(Tabela4[[#This Row],[projeto_nome]],projetos!B:B,projetos!C:C)) -> Automações RPA | G7: =_xlfn.XLOOKUP(F7,dim_custo_setor_horas!$E$1:$E$8,dim_custo_setor_horas!$F$1:$F$8," ") -> 12 | H7: =IF(Tabela4[[#This Row],[projeto_nome]]=0," ",_xlfn.XLOOKUP(Tabela4[[#This Row],[projeto_id]],projetos!A:A,projetos!N:N," ")) -> 46118 | I7: =_xlfn.XLOOKUP(Tabela4[[#This Row],[projeto_id]],projetos!A:A,projetos!O:O," ") -> 46178 | J7: 2
A8: ALO-008 | B8: =IFERROR(_xlfn.XLOOKUP(Tabela4[[#This Row],[membro_nome]],Tabela3[nome],Tabela3[id])," ") -> MBR-002 | C8: Rafael Souza | D8: =IFERROR(_xlfn.XLOOKUP(Tabela4[[#This Row],[projeto_nome]],projetos!B:B,projetos!A:A)," ") -> PRJ-006 | E8: Sistema Stratws One | F8: =IF(Tabela4[[#This Row],[projeto_nome]]=0," ",_xlfn.XLOOKUP(Tabela4[[#This Row],[projeto_nome]],projetos!B:B,projetos!C:C)) -> Software | G8: 7 | H8: =IF(Tabela4[[#This Row],[projeto_nome]]=0," ",_xlfn.XLOOKUP(Tabela4[[#This Row],[projeto_id]],projetos!A:A,projetos!N:N," ")) -> 46054 | I8: =_xlfn.XLOOKUP(Tabela4[[#This Row],[projeto_id]],projetos!A:A,projetos!O:O," ") -> 46171 | J8: 1
A9: ALO-015 | B9: =IFERROR(_xlfn.XLOOKUP(Tabela4[[#This Row],[membro_nome]],Tabela3[nome],Tabela3[id])," ") -> MBR-002 | C9: Rafael Souza | D9: =IF(Tabela4[[#This Row],[projeto_nome]]=0," ",_xlfn.XLOOKUP(Tabela4[[#This Row],[projeto_nome]],projetos!B:B,projetos!A:A)) -> PRJ-005 | E9: Data Lake DELP | F9: =IF(Tabela4[[#This Row],[projeto_nome]]=0," ",_xlfn.XLOOKUP(Tabela4[[#This Row],[projeto_nome]],projetos!B:B,projetos!C:C)) -> Software | G9: 7 | H9: =IF(Tabela4[[#This Row],[projeto_nome]]=0," ",_xlfn.XLOOKUP(Tabela4[[#This Row],[projeto_id]],projetos!A:A,projetos!N:N," ")) -> 46054 | I9: =_xlfn.XLOOKUP(Tabela4[[#This Row],[projeto_id]],projetos!A:A,projetos!O:O," ") -> 46188 | J9: 1
A10: ALO-010 | B10: =IFERROR(_xlfn.XLOOKUP(Tabela4[[#This Row],[membro_nome]],Tabela3[nome],Tabela3[id])," ") -> MBR-002 | C10: Rafael Souza | D10: =IF(Tabela4[[#This Row],[projeto_nome]]=0," ",_xlfn.XLOOKUP(Tabela4[[#This Row],[projeto_nome]],projetos!B:B,projetos!A:A)) | F10: =IF(Tabela4[[#This Row],[projeto_nome]]=0," ",_xlfn.XLOOKUP(Tabela4[[#This Row],[projeto_nome]],projetos!B:B,projetos!C:C)) | G10: =_xlfn.XLOOKUP(F10,dim_custo_setor_horas!$E$1:$E$8,dim_custo_setor_horas!$F$1:$F$8," ") | H10: =IF(Tabela4[[#This Row],[projeto_nome]]=0," ",_xlfn.XLOOKUP(Tabela4[[#This Row],[projeto_id]],projetos!A:A,projetos!N:N," ")) | I10: =_xlfn.XLOOKUP(Tabela4[[#This Row],[projeto_id]],projetos!A:A,projetos!O:O," ") | J10: 1
A11: ALO-013 | B11: =IFERROR(_xlfn.XLOOKUP(Tabela4[[#This Row],[membro_nome]],Tabela3[nome],Tabela3[id])," ") -> MBR-002 | C11: Rafael Souza | D11: =IF(Tabela4[[#This Row],[projeto_nome]]=0," ",_xlfn.XLOOKUP(Tabela4[[#This Row],[projeto_nome]],projetos!B:B,projetos!A:A)) | F11: =IF(Tabela4[[#This Row],[projeto_nome]]=0," ",_xlfn.XLOOKUP(Tabela4[[#This Row],[projeto_nome]],projetos!B:B,projetos!C:C)) | G11: =_xlfn.XLOOKUP(F11,dim_custo_setor_horas!$E$1:$E$8,dim_custo_setor_horas!$F$1:$F$8," ") | H11: =IF(Tabela4[[#This Row],[projeto_nome]]=0," ",_xlfn.XLOOKUP(Tabela4[[#This Row],[projeto_id]],projetos!A:A,projetos!N:N," ")) | I11: =_xlfn.XLOOKUP(Tabela4[[#This Row],[projeto_id]],projetos!A:A,projetos!O:O," ") | J11: 1
A12: ALO-001 | B12: =IFERROR(_xlfn.XLOOKUP(Tabela4[[#This Row],[membro_nome]],Tabela3[nome],Tabela3[id])," ") -> MBR-002 | C12: Rafael Souza | D12: =IF(Tabela4[[#This Row],[projeto_nome]]=0," ",_xlfn.XLOOKUP(Tabela4[[#This Row],[projeto_nome]],projetos!B:B,projetos!A:A)) | F12: =IF(Tabela4[[#This Row],[projeto_nome]]=0," ",_xlfn.XLOOKUP(Tabela4[[#This Row],[projeto_nome]],projetos!B:B,projetos!C:C)) | G12: =_xlfn.XLOOKUP(F12,dim_custo_setor_horas!$E$1:$E$8,dim_custo_setor_horas!$F$1:$F$8," ") | H12: =IF(Tabela4[[#This Row],[projeto_nome]]=0," ",_xlfn.XLOOKUP(Tabela4[[#This Row],[projeto_id]],projetos!A:A,projetos!N:N," ")) | I12: =_xlfn.XLOOKUP(Tabela4[[#This Row],[projeto_id]],projetos!A:A,projetos!O:O," ") | J12: 1
A13: ALO-012 | B13: =IFERROR(_xlfn.XLOOKUP(Tabela4[[#This Row],[membro_nome]],Tabela3[nome],Tabela3[id])," ") -> MBR-003 | C13: Lucas Franca | D13: =IF(Tabela4[[#This Row],[projeto_nome]]=0," ",_xlfn.XLOOKUP(Tabela4[[#This Row],[projeto_nome]],projetos!B:B,projetos!A:A)) -> PRJ-003 | E13: SOC | F13: =IF(Tabela4[[#This Row],[projeto_nome]]=0," ",_xlfn.XLOOKUP(Tabela4[[#This Row],[projeto_nome]],projetos!B:B,projetos!C:C)) -> Software | G13: =_xlfn.XLOOKUP(F13,dim_custo_setor_horas!$E$1:$E$8,dim_custo_setor_horas!$F$1:$F$8," ") -> 6 | H13: =IF(Tabela4[[#This Row],[projeto_nome]]=0," ",_xlfn.XLOOKUP(Tabela4[[#This Row],[projeto_id]],projetos!A:A,projetos!N:N," ")) -> 46023 | I13: =_xlfn.XLOOKUP(Tabela4[[#This Row],[projeto_id]],projetos!A:A,projetos!O:O," ") -> 46172 | J13: 1
A14: ALO-003 | B14: =IFERROR(_xlfn.XLOOKUP(Tabela4[[#This Row],[membro_nome]],Tabela3[nome],Tabela3[id])," ") -> MBR-003 | C14: Lucas Franca | D14: =IF(Tabela4[[#This Row],[projeto_nome]]=0," ",_xlfn.XLOOKUP(Tabela4[[#This Row],[projeto_nome]],projetos!B:B,projetos!A:A)) -> PRJ-007 | E14: Databook Digital Fase 2 | F14: =IF(Tabela4[[#This Row],[projeto_nome]]=0," ",_xlfn.XLOOKUP(Tabela4[[#This Row],[projeto_nome]],projetos!B:B,projetos!C:C)) -> Software | G14: 8 | H14: =IF(Tabela4[[#This Row],[projeto_nome]]=0," ",_xlfn.XLOOKUP(Tabela4[[#This Row],[projeto_id]],projetos!A:A,projetos!N:N," ")) -> 45992 | I14: =_xlfn.XLOOKUP(Tabela4[[#This Row],[projeto_id]],projetos!A:A,projetos!O:O," ") -> 46266 | J14: 1
A15: ALO-004 | B15: =IFERROR(_xlfn.XLOOKUP(Tabela4[[#This Row],[membro_nome]],Tabela3[nome],Tabela3[id])," ") -> MBR-003 | C15: Lucas Franca | D15: =IF(Tabela4[[#This Row],[projeto_nome]]=0," ",_xlfn.XLOOKUP(Tabela4[[#This Row],[projeto_nome]],projetos!B:B,projetos!A:A)) -> PRJ-014 | E15: Reformulação Delp Ideia | F15: =IF(Tabela4[[#This Row],[projeto_nome]]=0," ",_xlfn.XLOOKUP(Tabela4[[#This Row],[projeto_nome]],projetos!B:B,projetos!C:C)) -> BI & Eng. Dados | G15: 10 | H15: =IF(Tabela4[[#This Row],[projeto_nome]]=0," ",_xlfn.XLOOKUP(Tabela4[[#This Row],[projeto_id]],projetos!A:A,projetos!N:N," ")) -> 46062 | I15: =_xlfn.XLOOKUP(Tabela4[[#This Row],[projeto_id]],projetos!A:A,projetos!O:O," ") -> 46142 | J15: 1
A16: ALO-021 | B16: =IFERROR(_xlfn.XLOOKUP(Tabela4[[#This Row],[membro_nome]],Tabela3[nome],Tabela3[id])," ") -> MBR-003 | C16: Lucas Franca | D16: =IF(Tabela4[[#This Row],[projeto_nome]]=0," ",_xlfn.XLOOKUP(Tabela4[[#This Row],[projeto_nome]],projetos!B:B,projetos!A:A)) -> PRJ-034 | E16: Calibre Analytics Metrologia | F16: =IF(Tabela4[[#This Row],[projeto_nome]]=0," ",_xlfn.XLOOKUP(Tabela4[[#This Row],[projeto_nome]],projetos!B:B,projetos!C:C)) -> BI & Eng. Dados | G16: 6 | H16: =IF(Tabela4[[#This Row],[projeto_nome]]=0," ",_xlfn.XLOOKUP(Tabela4[[#This Row],[projeto_id]],projetos!A:A,projetos!N:N," ")) -> 46105 | I16: =_xlfn.XLOOKUP(Tabela4[[#This Row],[projeto_id]],projetos!A:A,projetos!O:O," ") -> 46164 | J16: 1
A17: ALO-014 | B17: =IFERROR(_xlfn.XLOOKUP(Tabela4[[#This Row],[membro_nome]],Tabela3[nome],Tabela3[id])," ") -> MBR-003 | C17: Lucas Franca | D17: =IF(Tabela4[[#This Row],[projeto_nome]]=0," ",_xlfn.XLOOKUP(Tabela4[[#This Row],[projeto_nome]],projetos!B:B,projetos!A:A)) -> PRJ-029 | E17: Melhorias Core (BI - Registro da Qualidade) | F17: =IF(Tabela4[[#This Row],[projeto_nome]]=0," ",_xlfn.XLOOKUP(Tabela4[[#This Row],[projeto_nome]],projetos!B:B,projetos!C:C)) -> BI & Eng. Dados | G17: 5 | H17: =IF(Tabela4[[#This Row],[projeto_nome]]=0," ",_xlfn.XLOOKUP(Tabela4[[#This Row],[projeto_id]],projetos!A:A,projetos!N:N," ")) -> 46076 | I17: =_xlfn.XLOOKUP(Tabela4[[#This Row],[projeto_id]],projetos!A:A,projetos!O:O," ") -> 46087 | J17: 1
A18: ALO-023 | B18: =IFERROR(_xlfn.XLOOKUP(Tabela4[[#This Row],[membro_nome]],Tabela3[nome],Tabela3[id])," ") -> MBR-004 | C18: Luiz Castro | D18: =IF(Tabela4[[#This Row],[projeto_nome]]=0," ",_xlfn.XLOOKUP(Tabela4[[#This Row],[projeto_nome]],projetos!B:B,projetos!A:A)) -> PRJ-026 | E18: Automação - Visão da rotina | F18: =IF(Tabela4[[#This Row],[projeto_nome]]=0," ",_xlfn.XLOOKUP(Tabela4[[#This Row],[projeto_nome]],projetos!B:B,projetos!C:C)) -> Automações RPA | G18: =_xlfn.XLOOKUP(F18,dim_custo_setor_horas!$E$1:$E$8,dim_custo_setor_horas!$F$1:$F$8," ") -> 12 | H18: =IF(Tabela4[[#This Row],[projeto_nome]]=0," ",_xlfn.XLOOKUP(Tabela4[[#This Row],[projeto_id]],projetos!A:A,projetos!N:N," ")) -> 46063 | I18: =_xlfn.XLOOKUP(Tabela4[[#This Row],[projeto_id]],projetos!A:A,projetos!O:O," ") -> 46068 | J18: 1
A19: ALO-009 | B19: =IFERROR(_xlfn.XLOOKUP(Tabela4[[#This Row],[membro_nome]],Tabela3[nome],Tabela3[id])," ") -> MBR-004 | C19: Luiz Castro | D19: =IF(Tabela4[[#This Row],[projeto_nome]]=0," ",_xlfn.XLOOKUP(Tabela4[[#This Row],[projeto_nome]],projetos!B:B,projetos!A:A)) -> PRJ-024 | E19: Automação - Eficiência por célula | F19: =IF(Tabela4[[#This Row],[projeto_nome]]=0," ",_xlfn.XLOOKUP(Tabela4[[#This Row],[projeto_nome]],projetos!B:B,projetos!C:C)) -> Automações RPA | G19: =_xlfn.XLOOKUP(F19,dim_custo_setor_horas!$E$1:$E$8,dim_custo_setor_horas!$F$1:$F$8," ") -> 12 | H19: =IF(Tabela4[[#This Row],[projeto_nome]]=0," ",_xlfn.XLOOKUP(Tabela4[[#This Row],[projeto_id]],projetos!A:A,projetos!N:N," ")) -> 46063 | I19: =_xlfn.XLOOKUP(Tabela4[[#This Row],[projeto_id]],projetos!A:A,projetos!O:O," ") -> 46068 | J19: 1
A20: ALO-024 | B20: =IFERROR(_xlfn.XLOOKUP(Tabela4[[#This Row],[membro_nome]],Tabela3[nome],Tabela3[id])," ") -> MBR-004 | C20: Luiz Castro | D20: =IF(Tabela4[[#This Row],[projeto_nome]]=0," ",_xlfn.XLOOKUP(Tabela4[[#This Row],[projeto_nome]],projetos!B:B,projetos!A:A)) -> PRJ-004 | E20: Apontamento Digital | F20: =IF(Tabela4[[#This Row],[projeto_nome]]=0," ",_xlfn.XLOOKUP(Tabela4[[#This Row],[projeto_nome]],projetos!B:B,projetos!C:C)) -> Software | G20: 20 | H20: =IF(Tabela4[[#This Row],[projeto_nome]]=0," ",_xlfn.XLOOKUP(Tabela4[[#This Row],[projeto_id]],projetos!A:A,projetos!N:N," ")) -> 45992 | I20: =_xlfn.XLOOKUP(Tabela4[[#This Row],[projeto_id]],projetos!A:A,projetos!O:O," ") -> 46356 | J20: 1
A21: ALO-006 | B21: =IFERROR(_xlfn.XLOOKUP(Tabela4[[#This Row],[membro_nome]],Tabela3[nome],Tabela3[id])," ") -> MBR-004 | C21: Luiz Castro | D21: =IF(Tabela4[[#This Row],[projeto_nome]]=0," ",_xlfn.XLOOKUP(Tabela4[[#This Row],[projeto_nome]],projetos!B:B,projetos!A:A)) -> PRJ-028 | E21: Layout Fabril Automático | F21: =IF(Tabela4[[#This Row],[projeto_nome]]=0," ",_xlfn.XLOOKUP(Tabela4[[#This Row],[projeto_nome]],projetos!B:B,projetos!C:C)) -> Software | G21: =_xlfn.XLOOKUP(F21,dim_custo_setor_horas!$E$1:$E$8,dim_custo_setor_horas!$F$1:$F$8," ") -> 6 | H21: =IF(Tabela4[[#This Row],[projeto_nome]]=0," ",_xlfn.XLOOKUP(Tabela4[[#This Row],[projeto_id]],projetos!A:A,projetos!N:N," ")) -> 46113 | I21: =_xlfn.XLOOKUP(Tabela4[[#This Row],[projeto_id]],projetos!A:A,projetos!O:O," ") -> 46174 | J21: 1
A22: ALO-022 | B22: =IFERROR(_xlfn.XLOOKUP(Tabela4[[#This Row],[membro_nome]],Tabela3[nome],Tabela3[id])," ") -> MBR-004 | C22: Luiz Castro | D22: =IF(Tabela4[[#This Row],[projeto_nome]]=0," ",_xlfn.XLOOKUP(Tabela4[[#This Row],[projeto_nome]],projetos!B:B,projetos!A:A)) -> PRJ-036 | E22: Automatização Adm Fábrica | F22: =IF(Tabela4[[#This Row],[projeto_nome]]=0," ",_xlfn.XLOOKUP(Tabela4[[#This Row],[projeto_nome]],projetos!B:B,projetos!C:C)) -> Automações RPA | G22: 15 | H22: =IF(Tabela4[[#This Row],[projeto_nome]]=0," ",_xlfn.XLOOKUP(Tabela4[[#This Row],[projeto_id]],projetos!A:A,projetos!N:N," ")) -> 46118 | I22: =_xlfn.XLOOKUP(Tabela4[[#This Row],[projeto_id]],projetos!A:A,projetos!O:O," ") -> 46178 | J22: 1
A23: ALO-023 | B23: =IFERROR(_xlfn.XLOOKUP(Tabela4[[#This Row],[membro_nome]],Tabela3[nome],Tabela3[id])," ") -> MBR-005 | C23: César | D23: =IF(Tabela4[[#This Row],[projeto_nome]]=0," ",_xlfn.XLOOKUP(Tabela4[[#This Row],[projeto_nome]],projetos!B:B,projetos!A:A)) -> PRJ-005 | E23: Data Lake DELP | F23: =IF(Tabela4[[#This Row],[projeto_nome]]=0," ",_xlfn.XLOOKUP(Tabela4[[#This Row],[projeto_nome]],projetos!B:B,projetos!C:C)) -> Software | G23: 16 | H23: 46082 | I23: =_xlfn.XLOOKUP(Tabela4[[#This Row],[projeto_id]],projetos!A:A,projetos!O:O," ") -> 46188 | J23: 1
A24: ALO-024 | B24: =IFERROR(_xlfn.XLOOKUP(Tabela4[[#This Row],[membro_nome]],Tabela3[nome],Tabela3[id])," ") -> MBR-005 | C24: César | D24: =IF(Tabela4[[#This Row],[projeto_nome]]=0," ",_xlfn.XLOOKUP(Tabela4[[#This Row],[projeto_nome]],projetos!B:B,projetos!A:A)) -> PRJ-003 | E24: SOC | F24: =IF(Tabela4[[#This Row],[projeto_nome]]=0," ",_xlfn.XLOOKUP(Tabela4[[#This Row],[projeto_nome]],projetos!B:B,projetos!C:C)) -> Software | G24: =_xlfn.XLOOKUP(F24,dim_custo_setor_horas!$E$1:$E$8,dim_custo_setor_horas!$F$1:$F$8," ") -> 6 | H24: =IF(Tabela4[[#This Row],[projeto_nome]]=0," ",_xlfn.XLOOKUP(Tabela4[[#This Row],[projeto_id]],projetos!A:A,projetos!N:N," ")) -> 46023 | I24: =_xlfn.XLOOKUP(Tabela4[[#This Row],[projeto_id]],projetos!A:A,projetos!O:O," ") -> 46172 | J24: 1
A25: ALO-025 | B25: =IFERROR(_xlfn.XLOOKUP(Tabela4[[#This Row],[membro_nome]],Tabela3[nome],Tabela3[id])," ") -> MBR-005 | C25: César | D25: =IF(Tabela4[[#This Row],[projeto_nome]]=0," ",_xlfn.XLOOKUP(Tabela4[[#This Row],[projeto_nome]],projetos!B:B,projetos!A:A)) -> PRJ-004 | E25: Apontamento Digital | F25: =IF(Tabela4[[#This Row],[projeto_nome]]=0," ",_xlfn.XLOOKUP(Tabela4[[#This Row],[projeto_nome]],projetos!B:B,projetos!C:C)) -> Software | G25: =_xlfn.XLOOKUP(F25,dim_custo_setor_horas!$E$1:$E$8,dim_custo_setor_horas!$F$1:$F$8," ") -> 6 | H25: =IF(Tabela4[[#This Row],[projeto_nome]]=0," ",_xlfn.XLOOKUP(Tabela4[[#This Row],[projeto_id]],projetos!A:A,projetos!N:N," ")) -> 45992 | I25: =_xlfn.XLOOKUP(Tabela4[[#This Row],[projeto_id]],projetos!A:A,projetos!O:O," ") -> 46356 | J25: 1
A26: ALO-026 | B26: =IFERROR(_xlfn.XLOOKUP(Tabela4[[#This Row],[membro_nome]],Tabela3[nome],Tabela3[id])," ") -> 0 | D26: =IF(Tabela4[[#This Row],[projeto_nome]]=0," ",_xlfn.XLOOKUP(Tabela4[[#This Row],[projeto_nome]],projetos!B:B,projetos!A:A)) | F26: =IF(Tabela4[[#This Row],[projeto_nome]]=0," ",_xlfn.XLOOKUP(Tabela4[[#This Row],[projeto_nome]],projetos!B:B,projetos!C:C)) | G26: =_xlfn.XLOOKUP(F26,dim_custo_setor_horas!$E$1:$E$8,dim_custo_setor_horas!$F$1:$F$8," ") | H26: =IF(Tabela4[[#This Row],[projeto_nome]]=0," ",_xlfn.XLOOKUP(Tabela4[[#This Row],[projeto_id]],projetos!A:A,projetos!N:N," ")) | I26: =_xlfn.XLOOKUP(Tabela4[[#This Row],[projeto_id]],projetos!A:A,projetos!O:O," ") | J26: 1
A27: ALO-027 | B27: =IFERROR(_xlfn.XLOOKUP(Tabela4[[#This Row],[membro_nome]],Tabela3[nome],Tabela3[id])," ") -> 0 | D27: =IF(Tabela4[[#This Row],[projeto_nome]]=0," ",_xlfn.XLOOKUP(Tabela4[[#This Row],[projeto_nome]],projetos!B:B,projetos!A:A)) | F27: =IF(Tabela4[[#This Row],[projeto_nome]]=0," ",_xlfn.XLOOKUP(Tabela4[[#This Row],[projeto_nome]],projetos!B:B,projetos!C:C)) | G27: =_xlfn.XLOOKUP(F27,dim_custo_setor_horas!$E$1:$E$8,dim_custo_setor_horas!$F$1:$F$8," ") | H27: =IF(Tabela4[[#This Row],[projeto_nome]]=0," ",_xlfn.XLOOKUP(Tabela4[[#This Row],[projeto_id]],projetos!A:A,projetos!N:N," ")) | I27: =_xlfn.XLOOKUP(Tabela4[[#This Row],[projeto_id]],projetos!A:A,projetos!O:O," ") | J27: 0
A28: ALO-028 | B28: =IFERROR(_xlfn.XLOOKUP(Tabela4[[#This Row],[membro_nome]],Tabela3[nome],Tabela3[id])," ") -> 0 | D28: =IF(Tabela4[[#This Row],[projeto_nome]]=0," ",_xlfn.XLOOKUP(Tabela4[[#This Row],[projeto_nome]],projetos!B:B,projetos!A:A)) | F28: =IF(Tabela4[[#This Row],[projeto_nome]]=0," ",_xlfn.XLOOKUP(Tabela4[[#This Row],[projeto_nome]],projetos!B:B,projetos!C:C)) | G28: =_xlfn.XLOOKUP(F28,dim_custo_setor_horas!$E$1:$E$8,dim_custo_setor_horas!$F$1:$F$8," ") | H28: =IF(Tabela4[[#This Row],[projeto_nome]]=0," ",_xlfn.XLOOKUP(Tabela4[[#This Row],[projeto_id]],projetos!A:A,projetos!N:N," ")) | I28: =_xlfn.XLOOKUP(Tabela4[[#This Row],[projeto_id]],projetos!A:A,projetos!O:O," ") | J28: 0
A29: ALO-029 | B29: =IFERROR(_xlfn.XLOOKUP(Tabela4[[#This Row],[membro_nome]],Tabela3[nome],Tabela3[id])," ") -> 0 | D29: =IF(Tabela4[[#This Row],[projeto_nome]]=0," ",_xlfn.XLOOKUP(Tabela4[[#This Row],[projeto_nome]],projetos!B:B,projetos!A:A)) | F29: =IF(Tabela4[[#This Row],[projeto_nome]]=0," ",_xlfn.XLOOKUP(Tabela4[[#This Row],[projeto_nome]],projetos!B:B,projetos!C:C)) | G29: =_xlfn.XLOOKUP(F29,dim_custo_setor_horas!$E$1:$E$8,dim_custo_setor_horas!$F$1:$F$8," ") | H29: =IF(Tabela4[[#This Row],[projeto_nome]]=0," ",_xlfn.XLOOKUP(Tabela4[[#This Row],[projeto_id]],projetos!A:A,projetos!N:N," ")) | I29: =_xlfn.XLOOKUP(Tabela4[[#This Row],[projeto_id]],projetos!A:A,projetos!O:O," ") | J29: 0
A30: ALO-030 | B30: =IFERROR(_xlfn.XLOOKUP(Tabela4[[#This Row],[membro_nome]],Tabela3[nome],Tabela3[id])," ") -> 0 | D30: =IF(Tabela4[[#This Row],[projeto_nome]]=0," ",_xlfn.XLOOKUP(Tabela4[[#This Row],[projeto_nome]],projetos!B:B,projetos!A:A)) | F30: =IF(Tabela4[[#This Row],[projeto_nome]]=0," ",_xlfn.XLOOKUP(Tabela4[[#This Row],[projeto_nome]],projetos!B:B,projetos!C:C)) | H30: =IF(Tabela4[[#This Row],[projeto_nome]]=0," ",_xlfn.XLOOKUP(Tabela4[[#This Row],[projeto_id]],projetos!A:A,projetos!N:N," ")) | I30: =_xlfn.XLOOKUP(Tabela4[[#This Row],[projeto_id]],projetos!A:A,projetos!O:O," ") | J30: 0
A31: ALO-031 | B31: =IFERROR(_xlfn.XLOOKUP(Tabela4[[#This Row],[membro_nome]],Tabela3[nome],Tabela3[id])," ") -> 0 | D31: =IF(Tabela4[[#This Row],[projeto_nome]]=0," ",_xlfn.XLOOKUP(Tabela4[[#This Row],[projeto_nome]],projetos!B:B,projetos!A:A)) | F31: =IF(Tabela4[[#This Row],[projeto_nome]]=0," ",_xlfn.XLOOKUP(Tabela4[[#This Row],[projeto_nome]],projetos!B:B,projetos!C:C)) | G31: =_xlfn.XLOOKUP(F31,dim_custo_setor_horas!$E$1:$E$8,dim_custo_setor_horas!$F$1:$F$8," ") | H31: =IF(Tabela4[[#This Row],[projeto_nome]]=0," ",_xlfn.XLOOKUP(Tabela4[[#This Row],[projeto_id]],projetos!A:A,projetos!N:N," ")) | I31: =_xlfn.XLOOKUP(Tabela4[[#This Row],[projeto_id]],projetos!A:A,projetos!O:O," ") | J31: 0
A32: ALO-032 | B32: =IFERROR(_xlfn.XLOOKUP(Tabela4[[#This Row],[membro_nome]],Tabela3[nome],Tabela3[id])," ") -> 0 | D32: =IF(Tabela4[[#This Row],[projeto_nome]]=0," ",_xlfn.XLOOKUP(Tabela4[[#This Row],[projeto_nome]],projetos!B:B,projetos!A:A)) | F32: =IF(Tabela4[[#This Row],[projeto_nome]]=0," ",_xlfn.XLOOKUP(Tabela4[[#This Row],[projeto_nome]],projetos!B:B,projetos!C:C)) | G32: =_xlfn.XLOOKUP(F32,dim_custo_setor_horas!$E$1:$E$8,dim_custo_setor_horas!$F$1:$F$8," ") | H32: =IF(Tabela4[[#This Row],[projeto_nome]]=0," ",_xlfn.XLOOKUP(Tabela4[[#This Row],[projeto_id]],projetos!A:A,projetos!N:N," ")) | I32: =_xlfn.XLOOKUP(Tabela4[[#This Row],[projeto_id]],projetos!A:A,projetos!O:O," ") | J32: 0
A33: ALO-033 | B33: =IFERROR(_xlfn.XLOOKUP(Tabela4[[#This Row],[membro_nome]],Tabela3[nome],Tabela3[id])," ") -> 0 | D33: =IF(Tabela4[[#This Row],[projeto_nome]]=0," ",_xlfn.XLOOKUP(Tabela4[[#This Row],[projeto_nome]],projetos!B:B,projetos!A:A)) | F33: =IF(Tabela4[[#This Row],[projeto_nome]]=0," ",_xlfn.XLOOKUP(Tabela4[[#This Row],[projeto_nome]],projetos!B:B,projetos!C:C)) | G33: =_xlfn.XLOOKUP(F33,dim_custo_setor_horas!$E$1:$E$8,dim_custo_setor_horas!$F$1:$F$8," ") | H33: =IF(Tabela4[[#This Row],[projeto_nome]]=0," ",_xlfn.XLOOKUP(Tabela4[[#This Row],[projeto_id]],projetos!A:A,projetos!N:N," ")) | I33: =_xlfn.XLOOKUP(Tabela4[[#This Row],[projeto_id]],projetos!A:A,projetos!O:O," ") | J33: 0
A34: ALO-034 | B34: =IFERROR(_xlfn.XLOOKUP(Tabela4[[#This Row],[membro_nome]],Tabela3[nome],Tabela3[id])," ") -> 0 | D34: =IF(Tabela4[[#This Row],[projeto_nome]]=0," ",_xlfn.XLOOKUP(Tabela4[[#This Row],[projeto_nome]],projetos!B:B,projetos!A:A)) | F34: =IF(Tabela4[[#This Row],[projeto_nome]]=0," ",_xlfn.XLOOKUP(Tabela4[[#This Row],[projeto_nome]],projetos!B:B,projetos!C:C)) | G34: =_xlfn.XLOOKUP(F34,dim_custo_setor_horas!$E$1:$E$8,dim_custo_setor_horas!$F$1:$F$8," ") | H34: =IF(Tabela4[[#This Row],[projeto_nome]]=0," ",_xlfn.XLOOKUP(Tabela4[[#This Row],[projeto_id]],projetos!A:A,projetos!N:N," ")) | I34: =_xlfn.XLOOKUP(Tabela4[[#This Row],[projeto_id]],projetos!A:A,projetos!O:O," ") | J34: 0
A35: ALO-035 | B35: =IFERROR(_xlfn.XLOOKUP(Tabela4[[#This Row],[membro_nome]],Tabela3[nome],Tabela3[id])," ") -> 0 | D35: =IF(Tabela4[[#This Row],[projeto_nome]]=0," ",_xlfn.XLOOKUP(Tabela4[[#This Row],[projeto_nome]],projetos!B:B,projetos!A:A)) | F35: =IF(Tabela4[[#This Row],[projeto_nome]]=0," ",_xlfn.XLOOKUP(Tabela4[[#This Row],[projeto_nome]],projetos!B:B,projetos!C:C)) | G35: =_xlfn.XLOOKUP(F35,dim_custo_setor_horas!$E$1:$E$8,dim_custo_setor_horas!$F$1:$F$8," ") | H35: =IF(Tabela4[[#This Row],[projeto_nome]]=0," ",_xlfn.XLOOKUP(Tabela4[[#This Row],[projeto_id]],projetos!A:A,projetos!N:N," ")) | I35: =_xlfn.XLOOKUP(Tabela4[[#This Row],[projeto_id]],projetos!A:A,projetos!O:O," ") | J35: 0
A36: ALO-036 | B36: =IFERROR(_xlfn.XLOOKUP(Tabela4[[#This Row],[membro_nome]],Tabela3[nome],Tabela3[id])," ") -> 0 | D36: =IF(Tabela4[[#This Row],[projeto_nome]]=0," ",_xlfn.XLOOKUP(Tabela4[[#This Row],[projeto_nome]],projetos!B:B,projetos!A:A)) | F36: =IF(Tabela4[[#This Row],[projeto_nome]]=0," ",_xlfn.XLOOKUP(Tabela4[[#This Row],[projeto_nome]],projetos!B:B,projetos!C:C)) | G36: =_xlfn.XLOOKUP(F36,dim_custo_setor_horas!$E$1:$E$8,dim_custo_setor_horas!$F$1:$F$8," ") | H36: =IF(Tabela4[[#This Row],[projeto_nome]]=0," ",_xlfn.XLOOKUP(Tabela4[[#This Row],[projeto_id]],projetos!A:A,projetos!N:N," ")) | I36: =_xlfn.XLOOKUP(Tabela4[[#This Row],[projeto_id]],projetos!A:A,projetos!O:O," ") | J36: 0
A37: ALO-037 | B37: =IFERROR(_xlfn.XLOOKUP(Tabela4[[#This Row],[membro_nome]],Tabela3[nome],Tabela3[id])," ") -> 0 | D37: =IF(Tabela4[[#This Row],[projeto_nome]]=0," ",_xlfn.XLOOKUP(Tabela4[[#This Row],[projeto_nome]],projetos!B:B,projetos!A:A)) | F37: =IF(Tabela4[[#This Row],[projeto_nome]]=0," ",_xlfn.XLOOKUP(Tabela4[[#This Row],[projeto_nome]],projetos!B:B,projetos!C:C)) | G37: =_xlfn.XLOOKUP(F37,dim_custo_setor_horas!$E$1:$E$8,dim_custo_setor_horas!$F$1:$F$8," ") | H37: =IF(Tabela4[[#This Row],[projeto_nome]]=0," ",_xlfn.XLOOKUP(Tabela4[[#This Row],[projeto_id]],projetos!A:A,projetos!N:N," ")) | I37: =_xlfn.XLOOKUP(Tabela4[[#This Row],[projeto_id]],projetos!A:A,projetos!O:O," ") | J37: 0
A38: ALO-038 | B38: =IFERROR(_xlfn.XLOOKUP(Tabela4[[#This Row],[membro_nome]],Tabela3[nome],Tabela3[id])," ") -> 0 | D38: =IF(Tabela4[[#This Row],[projeto_nome]]=0," ",_xlfn.XLOOKUP(Tabela4[[#This Row],[projeto_nome]],projetos!B:B,projetos!A:A)) | F38: =IF(Tabela4[[#This Row],[projeto_nome]]=0," ",_xlfn.XLOOKUP(Tabela4[[#This Row],[projeto_nome]],projetos!B:B,projetos!C:C)) | G38: =_xlfn.XLOOKUP(F38,dim_custo_setor_horas!$E$1:$E$8,dim_custo_setor_horas!$F$1:$F$8," ") | H38: =IF(Tabela4[[#This Row],[projeto_nome]]=0," ",_xlfn.XLOOKUP(Tabela4[[#This Row],[projeto_id]],projetos!A:A,projetos!N:N," ")) | I38: =_xlfn.XLOOKUP(Tabela4[[#This Row],[projeto_id]],projetos!A:A,projetos!O:O," ") | J38: 0
A39: ALO-039 | B39: =IFERROR(_xlfn.XLOOKUP(Tabela4[[#This Row],[membro_nome]],Tabela3[nome],Tabela3[id])," ") -> 0 | D39: =IF(Tabela4[[#This Row],[projeto_nome]]=0," ",_xlfn.XLOOKUP(Tabela4[[#This Row],[projeto_nome]],projetos!B:B,projetos!A:A)) | F39: =IF(Tabela4[[#This Row],[projeto_nome]]=0," ",_xlfn.XLOOKUP(Tabela4[[#This Row],[projeto_nome]],projetos!B:B,projetos!C:C)) | G39: =_xlfn.XLOOKUP(F39,dim_custo_setor_horas!$E$1:$E$8,dim_custo_setor_horas!$F$1:$F$8," ") | H39: =IF(Tabela4[[#This Row],[projeto_nome]]=0," ",_xlfn.XLOOKUP(Tabela4[[#This Row],[projeto_id]],projetos!A:A,projetos!N:N," ")) | I39: =_xlfn.XLOOKUP(Tabela4[[#This Row],[projeto_id]],projetos!A:A,projetos!O:O," ") | J39: 0
A40: ALO-040 | B40: =IFERROR(_xlfn.XLOOKUP(Tabela4[[#This Row],[membro_nome]],Tabela3[nome],Tabela3[id])," ") -> 0 | D40: =IF(Tabela4[[#This Row],[projeto_nome]]=0," ",_xlfn.XLOOKUP(Tabela4[[#This Row],[projeto_nome]],projetos!B:B,projetos!A:A)) | F40: =IF(Tabela4[[#This Row],[projeto_nome]]=0," ",_xlfn.XLOOKUP(Tabela4[[#This Row],[projeto_nome]],projetos!B:B,projetos!C:C)) | G40: =_xlfn.XLOOKUP(F40,dim_custo_setor_horas!$E$1:$E$8,dim_custo_setor_horas!$F$1:$F$8," ") | H40: =IF(Tabela4[[#This Row],[projeto_nome]]=0," ",_xlfn.XLOOKUP(Tabela4[[#This Row],[projeto_id]],projetos!A:A,projetos!N:N," ")) | I40: =_xlfn.XLOOKUP(Tabela4[[#This Row],[projeto_id]],projetos!A:A,projetos!O:O," ") | J40: 0
A41: ALO-041 | B41: =IFERROR(_xlfn.XLOOKUP(Tabela4[[#This Row],[membro_nome]],Tabela3[nome],Tabela3[id])," ") -> 0 | D41: =IF(Tabela4[[#This Row],[projeto_nome]]=0," ",_xlfn.XLOOKUP(Tabela4[[#This Row],[projeto_nome]],projetos!B:B,projetos!A:A)) | F41: =IF(Tabela4[[#This Row],[projeto_nome]]=0," ",_xlfn.XLOOKUP(Tabela4[[#This Row],[projeto_nome]],projetos!B:B,projetos!C:C)) | G41: =_xlfn.XLOOKUP(F41,dim_custo_setor_horas!$E$1:$E$8,dim_custo_setor_horas!$F$1:$F$8," ") | H41: =IF(Tabela4[[#This Row],[projeto_nome]]=0," ",_xlfn.XLOOKUP(Tabela4[[#This Row],[projeto_id]],projetos!A:A,projetos!N:N," ")) | I41: =_xlfn.XLOOKUP(Tabela4[[#This Row],[projeto_id]],projetos!A:A,projetos!O:O," ") | J41: 0
A42: ALO-042 | B42: =IFERROR(_xlfn.XLOOKUP(Tabela4[[#This Row],[membro_nome]],Tabela3[nome],Tabela3[id])," ") -> 0 | D42: =IF(Tabela4[[#This Row],[projeto_nome]]=0," ",_xlfn.XLOOKUP(Tabela4[[#This Row],[projeto_nome]],projetos!B:B,projetos!A:A)) | F42: =IF(Tabela4[[#This Row],[projeto_nome]]=0," ",_xlfn.XLOOKUP(Tabela4[[#This Row],[projeto_nome]],projetos!B:B,projetos!C:C)) | G42: =_xlfn.XLOOKUP(F42,dim_custo_setor_horas!$E$1:$E$8,dim_custo_setor_horas!$F$1:$F$8," ") | H42: =IF(Tabela4[[#This Row],[projeto_nome]]=0," ",_xlfn.XLOOKUP(Tabela4[[#This Row],[projeto_id]],projetos!A:A,projetos!N:N," ")) | I42: =_xlfn.XLOOKUP(Tabela4[[#This Row],[projeto_id]],projetos!A:A,projetos!O:O," ") | J42: 0
A43: ALO-043 | B43: =IFERROR(_xlfn.XLOOKUP(Tabela4[[#This Row],[membro_nome]],Tabela3[nome],Tabela3[id])," ") -> 0 | D43: =IF(Tabela4[[#This Row],[projeto_nome]]=0," ",_xlfn.XLOOKUP(Tabela4[[#This Row],[projeto_nome]],projetos!B:B,projetos!A:A)) | F43: =IF(Tabela4[[#This Row],[projeto_nome]]=0," ",_xlfn.XLOOKUP(Tabela4[[#This Row],[projeto_nome]],projetos!B:B,projetos!C:C)) | H43: =IF(Tabela4[[#This Row],[projeto_nome]]=0," ",_xlfn.XLOOKUP(Tabela4[[#This Row],[projeto_id]],projetos!A:A,projetos!N:N," ")) | I43: =_xlfn.XLOOKUP(Tabela4[[#This Row],[projeto_id]],projetos!A:A,projetos!O:O," ") | J43: 0
A44: ALO-044 | B44: =IFERROR(_xlfn.XLOOKUP(Tabela4[[#This Row],[membro_nome]],Tabela3[nome],Tabela3[id])," ") -> 0 | D44: =IF(Tabela4[[#This Row],[projeto_nome]]=0," ",_xlfn.XLOOKUP(Tabela4[[#This Row],[projeto_nome]],projetos!B:B,projetos!A:A)) | F44: =IF(Tabela4[[#This Row],[projeto_nome]]=0," ",_xlfn.XLOOKUP(Tabela4[[#This Row],[projeto_nome]],projetos!B:B,projetos!C:C)) | H44: =IF(Tabela4[[#This Row],[projeto_nome]]=0," ",_xlfn.XLOOKUP(Tabela4[[#This Row],[projeto_id]],projetos!A:A,projetos!N:N," ")) | I44: =_xlfn.XLOOKUP(Tabela4[[#This Row],[projeto_id]],projetos!A:A,projetos!O:O," ") | J44: 0
A45: ALO-045 | B45: =IFERROR(_xlfn.XLOOKUP(Tabela4[[#This Row],[membro_nome]],Tabela3[nome],Tabela3[id])," ") -> 0 | D45: =IF(Tabela4[[#This Row],[projeto_nome]]=0," ",_xlfn.XLOOKUP(Tabela4[[#This Row],[projeto_nome]],projetos!B:B,projetos!A:A)) | F45: =IF(Tabela4[[#This Row],[projeto_nome]]=0," ",_xlfn.XLOOKUP(Tabela4[[#This Row],[projeto_nome]],projetos!B:B,projetos!C:C)) | H45: =IF(Tabela4[[#This Row],[projeto_nome]]=0," ",_xlfn.XLOOKUP(Tabela4[[#This Row],[projeto_id]],projetos!A:A,projetos!N:N," ")) | I45: =_xlfn.XLOOKUP(Tabela4[[#This Row],[projeto_id]],projetos!A:A,projetos!O:O," ") | J45: 0
A46: ALO-046 | B46: =IFERROR(_xlfn.XLOOKUP(Tabela4[[#This Row],[membro_nome]],Tabela3[nome],Tabela3[id])," ") -> 0 | D46: =IF(Tabela4[[#This Row],[projeto_nome]]=0," ",_xlfn.XLOOKUP(Tabela4[[#This Row],[projeto_nome]],projetos!B:B,projetos!A:A)) | F46: =IF(Tabela4[[#This Row],[projeto_nome]]=0," ",_xlfn.XLOOKUP(Tabela4[[#This Row],[projeto_nome]],projetos!B:B,projetos!C:C)) | H46: =IF(Tabela4[[#This Row],[projeto_nome]]=0," ",_xlfn.XLOOKUP(Tabela4[[#This Row],[projeto_id]],projetos!A:A,projetos!N:N," ")) | I46: =_xlfn.XLOOKUP(Tabela4[[#This Row],[projeto_id]],projetos!A:A,projetos!O:O," ") | J46: 0
A47: ALO-047 | B47: =IFERROR(_xlfn.XLOOKUP(Tabela4[[#This Row],[membro_nome]],Tabela3[nome],Tabela3[id])," ") -> 0 | D47: =IF(Tabela4[[#This Row],[projeto_nome]]=0," ",_xlfn.XLOOKUP(Tabela4[[#This Row],[projeto_nome]],projetos!B:B,projetos!A:A)) | F47: =IF(Tabela4[[#This Row],[projeto_nome]]=0," ",_xlfn.XLOOKUP(Tabela4[[#This Row],[projeto_nome]],projetos!B:B,projetos!C:C)) | H47: =IF(Tabela4[[#This Row],[projeto_nome]]=0," ",_xlfn.XLOOKUP(Tabela4[[#This Row],[projeto_id]],projetos!A:A,projetos!N:N," ")) | I47: =_xlfn.XLOOKUP(Tabela4[[#This Row],[projeto_id]],projetos!A:A,projetos!O:O," ") | J47: 0
A48: ALO-048 | B48: =IFERROR(_xlfn.XLOOKUP(Tabela4[[#This Row],[membro_nome]],Tabela3[nome],Tabela3[id])," ") -> 0 | D48: =IF(Tabela4[[#This Row],[projeto_nome]]=0," ",_xlfn.XLOOKUP(Tabela4[[#This Row],[projeto_nome]],projetos!B:B,projetos!A:A)) | F48: =IF(Tabela4[[#This Row],[projeto_nome]]=0," ",_xlfn.XLOOKUP(Tabela4[[#This Row],[projeto_nome]],projetos!B:B,projetos!C:C)) | H48: =IF(Tabela4[[#This Row],[projeto_nome]]=0," ",_xlfn.XLOOKUP(Tabela4[[#This Row],[projeto_id]],projetos!A:A,projetos!N:N," ")) | I48: =_xlfn.XLOOKUP(Tabela4[[#This Row],[projeto_id]],projetos!A:A,projetos!O:O," ") | J48: 0
A49: ALO-049 | B49: =IFERROR(_xlfn.XLOOKUP(Tabela4[[#This Row],[membro_nome]],Tabela3[nome],Tabela3[id])," ") -> 0 | D49: =IF(Tabela4[[#This Row],[projeto_nome]]=0," ",_xlfn.XLOOKUP(Tabela4[[#This Row],[projeto_nome]],projetos!B:B,projetos!A:A)) | F49: =IF(Tabela4[[#This Row],[projeto_nome]]=0," ",_xlfn.XLOOKUP(Tabela4[[#This Row],[projeto_nome]],projetos!B:B,projetos!C:C)) | H49: =IF(Tabela4[[#This Row],[projeto_nome]]=0," ",_xlfn.XLOOKUP(Tabela4[[#This Row],[projeto_id]],projetos!A:A,projetos!N:N," ")) | I49: =_xlfn.XLOOKUP(Tabela4[[#This Row],[projeto_id]],projetos!A:A,projetos!O:O," ") | J49: 0
A50: ALO-050 | B50: =IFERROR(_xlfn.XLOOKUP(Tabela4[[#This Row],[membro_nome]],Tabela3[nome],Tabela3[id])," ") -> 0 | D50: =IF(Tabela4[[#This Row],[projeto_nome]]=0," ",_xlfn.XLOOKUP(Tabela4[[#This Row],[projeto_nome]],projetos!B:B,projetos!A:A)) | F50: =IF(Tabela4[[#This Row],[projeto_nome]]=0," ",_xlfn.XLOOKUP(Tabela4[[#This Row],[projeto_nome]],projetos!B:B,projetos!C:C)) | H50: =IF(Tabela4[[#This Row],[projeto_nome]]=0," ",_xlfn.XLOOKUP(Tabela4[[#This Row],[projeto_id]],projetos!A:A,projetos!N:N," ")) | I50: =_xlfn.XLOOKUP(Tabela4[[#This Row],[projeto_id]],projetos!A:A,projetos!O:O," ") | J50: 0
A51: ALO-051 | B51: =IFERROR(_xlfn.XLOOKUP(Tabela4[[#This Row],[membro_nome]],Tabela3[nome],Tabela3[id])," ") -> 0 | D51: =IF(Tabela4[[#This Row],[projeto_nome]]=0," ",_xlfn.XLOOKUP(Tabela4[[#This Row],[projeto_nome]],projetos!B:B,projetos!A:A)) | F51: =IF(Tabela4[[#This Row],[projeto_nome]]=0," ",_xlfn.XLOOKUP(Tabela4[[#This Row],[projeto_nome]],projetos!B:B,projetos!C:C)) | H51: =IF(Tabela4[[#This Row],[projeto_nome]]=0," ",_xlfn.XLOOKUP(Tabela4[[#This Row],[projeto_id]],projetos!A:A,projetos!N:N," ")) | I51: =_xlfn.XLOOKUP(Tabela4[[#This Row],[projeto_id]],projetos!A:A,projetos!O:O," ") | J51: 0
A52: ALO-052 | B52: =IFERROR(_xlfn.XLOOKUP(Tabela4[[#This Row],[membro_nome]],Tabela3[nome],Tabela3[id])," ") -> 0 | D52: =IF(Tabela4[[#This Row],[projeto_nome]]=0," ",_xlfn.XLOOKUP(Tabela4[[#This Row],[projeto_nome]],projetos!B:B,projetos!A:A)) | F52: =IF(Tabela4[[#This Row],[projeto_nome]]=0," ",_xlfn.XLOOKUP(Tabela4[[#This Row],[projeto_nome]],projetos!B:B,projetos!C:C)) | H52: =IF(Tabela4[[#This Row],[projeto_nome]]=0," ",_xlfn.XLOOKUP(Tabela4[[#This Row],[projeto_id]],projetos!A:A,projetos!N:N," ")) | I52: =_xlfn.XLOOKUP(Tabela4[[#This Row],[projeto_id]],projetos!A:A,projetos!O:O," ") | J52: 0
A53: ALO-053 | B53: =IFERROR(_xlfn.XLOOKUP(Tabela4[[#This Row],[membro_nome]],Tabela3[nome],Tabela3[id])," ") -> 0 | D53: =IF(Tabela4[[#This Row],[projeto_nome]]=0," ",_xlfn.XLOOKUP(Tabela4[[#This Row],[projeto_nome]],projetos!B:B,projetos!A:A)) | F53: =IF(Tabela4[[#This Row],[projeto_nome]]=0," ",_xlfn.XLOOKUP(Tabela4[[#This Row],[projeto_nome]],projetos!B:B,projetos!C:C)) | H53: =IF(Tabela4[[#This Row],[projeto_nome]]=0," ",_xlfn.XLOOKUP(Tabela4[[#This Row],[projeto_id]],projetos!A:A,projetos!N:N," ")) | I53: =_xlfn.XLOOKUP(Tabela4[[#This Row],[projeto_id]],projetos!A:A,projetos!O:O," ") | J53: 0
A54: ALO-054 | B54: =IFERROR(_xlfn.XLOOKUP(Tabela4[[#This Row],[membro_nome]],Tabela3[nome],Tabela3[id])," ") -> 0 | D54: =IF(Tabela4[[#This Row],[projeto_nome]]=0," ",_xlfn.XLOOKUP(Tabela4[[#This Row],[projeto_nome]],projetos!B:B,projetos!A:A)) | F54: =IF(Tabela4[[#This Row],[projeto_nome]]=0," ",_xlfn.XLOOKUP(Tabela4[[#This Row],[projeto_nome]],projetos!B:B,projetos!C:C)) | H54: =IF(Tabela4[[#This Row],[projeto_nome]]=0," ",_xlfn.XLOOKUP(Tabela4[[#This Row],[projeto_id]],projetos!A:A,projetos!N:N," ")) | I54: =_xlfn.XLOOKUP(Tabela4[[#This Row],[projeto_id]],projetos!A:A,projetos!O:O," ") | J54: 0
... A57: ALO-057 | B57: =IFERROR(_xlfn.XLOOKUP(Tabela4[[#This Row],[membro_nome]],Tabela3[nome],Tabela3[id])," ") -> 0 | D57: =IF(Tabela4[[#This Row],[projeto_nome]]=0," ",_xlfn.XLOOKUP(Tabela4[[#This Row],[projeto_nome]],projetos!B:B,projetos!A:A)) | F57: =IF(Tabela4[[#This Row],[projeto_nome]]=0," ",_xlfn.XLOOKUP(Tabela4[[#This Row],[projeto_nome]],projetos!B:B,projetos!C:C)) | H57: =IF(Tabela4[[#This Row],[projeto_nome]]=0," ",_xlfn.XLOOKUP(Tabela4[[#This Row],[projeto_id]],projetos!A:A,projetos!N:N," ")) | I57: =_xlfn.XLOOKUP(Tabela4[[#This Row],[projeto_id]],projetos!A:A,projetos!O:O," ") | J57: 0

Sheet dim_pessoas
A1: CODMO | B1: NOME | C1: funcao | D1: secao | E1: Contagem
A2: 00008 | B2: Mariana Zica Queiroz | C2: Conselheiro(a) Administrativo | D2: Conselho Administrativo - Filial | E2: 1
A3: 00009 | B3: Humberto Ribeiro de Mesquita Machado Zica | C3: Diretor Superintendente | D3: Conselho Administrativo - Filial | E3: 1
A4: 00010 | B4: Adriana Ribeiro M. Machado Zica | C4: Conselheiro(a) Administrativo | D4: Conselho Administrativo - Filial | E4: 1
A5: 00017 | B5: Josane Cristiano Brandao | C5: Diretor Industrial | D5: Diretoria - Filial | E5: 1
A6: 04518 | B6: Jose Bittencourt Mendes | C6: Desenhista Projetista I | D6: Gerência de Projetos - Filial | E6: 1
A7: 05451 | B7: Terezinha Candida Vale | C7: Auxiliar de Escritório | D7: Diretoria - Filial | E7: 1
A8: 06826 | B8: Jose Vicente Cordeiro | C8: Ajudante de Usinagem | D8: Usinagem Pesada - Filial | E8: 1
A9: 07149 | B9: Julio Teodoro da Silva | C9: Desempenador Especializado | D9: Pré-Montagem - Filial | E9: 2
A10: 07539 | B10: Carlos Rosa Tito | C10: Ajudante de Caldeiraria | D10: Solda Convencional | E10: 1
A11: 07614 | B11: Samuel Dias Fonseca | C11: Coordenador Técnico de Produção II | D11: Planejamento PCP - Filial | E11: 2
A12: 07745 | B12: Ricardo Alves Martins | C12: Caldeireiro III | D12: Pré-Montagem - Filial | E12: 2
A13: 07795 | B13: Antonio Carlos Luiz | C13: Soldador III | D13: Solda Convencional | E13: 1
... A844: 74421 | B844: Joao Victor da Silva Reis | C844: Auxiliar Técnico de CQ Documental I | D844: Controle de Qualidade Documental - Filial | E844: 1

Sheet dim_custo_setor_horas
A1: SEÇÃO | B1: CUSTO HORA | C1: IS_BACKOFFICE | E1: SQUAD | F1: HORAS / SEM
A2: Conselho Administrativo - Filial | B2: 0 | C2: 1 | E2: BI & Eng. Dados | F2: 20
A3: Diretoria - Filial | B3: 0 | C3: 1 | E3: Software | F3: 6
A4: Gerência de Projetos - Filial | B4: 108.25 | C4: 1 | E4: IA | F4: 20
A5: Usinagem Pesada - Filial | B5: 0 | C5: 0 | E5: Automações RPA | F5: 12
A6: Pré-Montagem - Filial | B6: 0 | C6: 0 | E6: Melhoria ERP | F6: 6
A7: Solda Convencional | B7: 83.73 | C7: 0 | E7: TOTAL
A8: Planejamento PCP - Filial | B8: 65.37 | C8: 0
A9: Logística - Filial | B9: 48.47 | C9: 0
A10: Preparação - Filial | B10: 0 | C10: 1
A11: SESMT – Segurança do Trabalho | B11: 61.77 | C11: 0
A12: Tecnologia da Informação - Filial | B12: 68.8 | C12: 1
A13: Gente e Gestão | B13: 100.86 | C13: 1
A14: Controle de Qualidade - Filial | B14: 74.61 | C14: 0
A15: Financeiro - Filial | B15: 80.58 | C15: 1
A16: Pesquisa e Desenvolvimento - P&D | B16: 115.82 | C16: 0
A17: Gerência da Produção - Filial RJ | B17: 170.21 | C17: 0
A18: Engenharia de Materiais e Solda - Filial | B18: 83.73 | C18: 0
A19: Almoxarifado - Filial | B19: 52.28 | C19: 1
... A54: Aprendiz - Filial | B54: 21.36 | C54: 0

Sheet validacao_lista
A1: id | B1: membro | C1: area | D1: status | E1: ordem_status | F1: etapa_cronograma | G1: ordem_cronograma
A2: PRJ-001 | B2: MBR-001 | C2: BI & Eng. Dados | D2: Backlog | E2: 1 | F2: Análise de viabilidade técnica | G2: 2
A3: PRJ-002 | B3: MBR-002 | C3: Software | D3: Triagem NID | E3: 2 | F3: Seleção de fornecedor | G3: 3
A4: PRJ-003 | B4: MBR-003 | C4: IA | D4: Prototipagem/BC | E4: 3 | F4: Entendimento e Planejamento | G4: 1
A5: PRJ-004 | B5: MBR-004 | C5: Automações RPA | D5: Planejamento | E5: 4 | F5: Coleta de Dados e Preparação do Ambiente | G5: 5
A6: PRJ-005 | B6: MBR-005 | C6: Melhoria ERP | D6: Execução | E6: 5 | F6: Validação, Testes e Otimização | G6: 6
A7: PRJ-006 | B7: MBR-006 | C7: Geral | D7: Go Live | E7: 6 | F7: Implantação e Monitoramento | G7: 7
A8: PRJ-007 | B8: MBR-007 | D8: Estabilização | E8: 7 | F8: Expansão | G8: 8
A9: PRJ-008 | B9: MBR-008 | D9: Encerrado | E9: 8 | F9: Assinatura de Contrato | G9: 4
A10: PRJ-009 | B10: MBR-009 | F10: Bloqueado | G10: 9
A11: PRJ-010 | B11: MBR-010
A12: PRJ-011 | B12: MBR-011
A13: PRJ-012 | B13: MBR-012
A14: PRJ-013 | B14: MBR-013
A15: PRJ-014 | B15: MBR-014
A16: PRJ-015 | B16: MBR-015
A17: PRJ-016 | B17: MBR-016
A18: PRJ-017 | B18: MBR-017
A19: PRJ-018 | B19: MBR-018
A20: PRJ-019 | B20: MBR-019
A21: PRJ-020 | B21: MBR-020
A22: PRJ-021 | B22: MBR-021
... A100: PRJ-100 | B100: MBR-100
A101: PRJ-101
A102: PRJ-102
A103: PRJ-103
A104: PRJ-104
A105: PRJ-105
A106: PRJ-106
A107: PRJ-107
A108: PRJ-108
A109: PRJ-109
A110: PRJ-110
A111: PRJ-111
A112: PRJ-112
... A500: PRJ-500

Sheet timesheets
A1: id | B1: membro_id | C1: projeto_id | D1: data_referencia | E1: horas | F1: cost_at_time
A2: TS-001 | B2: MBR-005 | C2: PRJ-001 | D2: 45600 | E2: 16 | F2: 65
A3: TS-002 | B3: MBR-005 | C3: PRJ-001 | D3: 45607 | E3: 20 | F3: 65
A4: TS-003 | B4: MBR-005 | C4: PRJ-001 | D4: 45614 | E4: 16 | F4: 65
A5: TS-004 | B5: MBR-005 | C5: PRJ-001 | D5: 45621 | E5: 16 | F5: 65
A6: TS-005 | B6: MBR-005 | C6: PRJ-001 | D6: 45628 | E6: 20 | F6: 65
A7: TS-006 | B7: MBR-005 | C7: PRJ-001 | D7: 45635 | E7: 16 | F7: 65
A8: TS-007 | B8: MBR-001 | C8: PRJ-001 | D8: 45600 | E8: 8 | F8: 95
A9: TS-008 | B9: MBR-001 | C9: PRJ-001 | D9: 45628 | E9: 8 | F9: 95
A10: TS-009 | B10: MBR-006 | C10: PRJ-002 | D10: 45600 | E10: 20 | F10: 65
A11: TS-010 | B11: MBR-006 | C11: PRJ-002 | D11: 45607 | E11: 20 | F11: 65
A12: TS-011 | B12: MBR-006 | C12: PRJ-002 | D12: 45628 | E12: 20 | F12: 65
A13: TS-012 | B13: MBR-006 | C13: PRJ-002 | D13: 45635 | E13: 16 | F13: 65
... A61: TS-060 | B61: MBR-001 | C61: PRJ-003 | D61: 45726 | E61: 6 | F61: 95

Sheet _dicionario
A1: DICIONÁRIO DE DADOS — NID DELP BI
A3: ABA | B3: COLUNA | C3: TIPO | D3: DESCRIÇÃO
A4: projetos | B4: id | C4: Texto | D4: Chave primária. Padrão: PRJ-001, PRJ-002...
A5: projetos | B5: nome | C5: Texto | D5: Nome completo do projeto
A6: projetos | B6: area | C6: Texto | D6: Dados / Software / IA / Automações / Melhoria ERP / Software ERP
A7: projetos | B7: status | C7: Texto | D7: backlog / em_andamento / concluido / bloqueado / cancelado
A8: projetos | B8: is_backoffice | C8: Inteiro | D8: 1 = projeto interno (backoffice) | 0 = estratégico Core Business
A9: projetos | B9: owner | C9: Texto | D9: Responsável técnico / facilitador do projeto (membro do NID)
A10: projetos | B10: sponsor | C10: Texto | D10: Sponsor executivo que aprovou e financia o projeto
A11: projetos | B11: prioridade | C11: Inteiro | D11: 1 = Alta | 2 = Média | 3 = Baixa
A12: projetos | B12: data_inicio / data_fim | C12: Data | D12: Planejado. Formato DD/MM/AAAA
A13: projetos | B13: data_inicio_real / data_fim_real | C13: Data | D13: Realizado. Deixar vazio enquanto não ocorrer
A14: projetos | B14: progresso_pct | C14: Inteiro | D14: 0 a 100 — percentual atual de conclusão do projeto
... A40: alocacoes | B40: is_active | C40: Inteiro | D40: 1 = alocação vigente | 0 = encerrada
A42: RELACIONAMENTOS POWER BI
B43: projetos[id] → timesheets[projeto_id] | C43: 1:* | D43: Single direction — dimensão filtra fato
B44: projetos[id] → alocacoes[projeto_id] | C44: 1:* | D44: Single direction — dimensão filtra fato
B45: membros_nucleo[id] → timesheets[membro_id] | C45: 1:* | D45: Single direction — dimensão filtra fato
B46: membros_nucleo[id] → alocacoes[membro_id] | C46: 1:* | D46: Single direction — dimensão filtra fato
A48: REGRAS DE INTEGRIDADE
B49: spent_capex ≤ budget_capex | C49: Regra de negócio | D49: Violação gera alerta de estouro orçamentário no BI
B50: Soma horas/semana por membro ≤ 40h | C50: Regra de negócio | D50: Sobrecarga gera alerta de capacidade no BI
B51: Projetos 'backlog' sem timesheets | C51: Regra de negócio | D51: Projeto não iniciado não gera horas reais
B52: cost_at_time = snapshot histórico | C52: Regra de dado | D52: Nunca atualizar retroativamente ao mudar custo/hora
